Workbook
Name Excel_BuiltIn_Print_Titles_2: 'IPDM_renda (IPARDES-PR)'!$A$3:$GX$3
Name indice02_07: #REF!

Sheet Dados Gerais Resumo Por Área
A1: Sistema Rodoviário Estadual de 2022 (Pavimentada + Não Pavimentada)
A2: Lotes | B2: Sup. Regional | C2: Área | D2: Ext. (km) | E2: Fator de Tráfego Média TMDA | F2: PIB per capita - R$ [2023] (IBGE 2022) | G2: IDHMédio (IBGE 2022) | H2: IDPM Geral 2022 (Renda/Educação/Saúde) (IPARDES 2022)
A3: 01 | B3: Leste | C3: A01 | D3: 200.62 | E3: =ROUNDUP(SUMIF('Fator Tráfego (DER-PR)'!$AR$6:$AR$1368,B3&" - "&C3,'Fator Tráfego (DER-PR)'!$AN$6:$AN$1368)/SUMIF('Fator Tráfego (DER-PR)'!$AR$6:$AR$1368,B3&" - "&C3,'Fator Tráfego (DER-PR)'!$J$6:$J$1368),0) -> 2926 | F3: =SUMIF('Dados Gerais por Municipio'!$L$3:$L$491,'Dados Gerais Resumo Por Área'!B3&" - "&'Dados Gerais Resumo Por Área'!C3,'Dados Gerais por Municipio'!$E$3:$E$491)/COUNTIF('Dados Gerais por Municipio'!$L$3:$L$491,'Dados Gerais Resumo Por Área'!B3&" - "&'Dados Gerais Resumo Por Área'!C3) -> 43217.723 | G3: =SUMIF('Dados Gerais por Municipio'!$L$3:$L$491,'Dados Gerais Resumo Por Área'!B3&" - "&'Dados Gerais Resumo Por Área'!C3,'Dados Gerais por Municipio'!$F$3:$F$491)/COUNTIF('Dados Gerais por Municipio'!$L$3:$L$491,'Dados Gerais Resumo Por Área'!B3&" - "&'Dados Gerais Resumo Por Área'!C3) -> 0.70225 | H3: =SUMIF('Dados Gerais por Municipio'!$L$3:$L$491,'Dados Gerais Resumo Por Área'!B3&" - "&'Dados Gerais Resumo Por Área'!C3,'Dados Gerais por Municipio'!$G$3:$G$491)/COUNTIF('Dados Gerais por Municipio'!$L$3:$L$491,'Dados Gerais Resumo Por Área'!B3&" - "&'Dados Gerais Resumo Por Área'!C3) -> 0.67216443
A4: 02 | B4: Leste | C4: A02 | D4: 237.45 | E4: =ROUNDUP(SUMIF('Fator Tráfego (DER-PR)'!$AR$6:$AR$1368,B4&" - "&C4,'Fator Tráfego (DER-PR)'!$AN$6:$AN$1368)/SUMIF('Fator Tráfego (DER-PR)'!$AR$6:$AR$1368,B4&" - "&C4,'Fator Tráfego (DER-PR)'!$J$6:$J$1368),0) -> 6166 | F4: =SUMIF('Dados Gerais por Municipio'!$L$3:$L$491,'Dados Gerais Resumo Por Área'!B4&" - "&'Dados Gerais Resumo Por Área'!C4,'Dados Gerais por Municipio'!$E$3:$E$491)/COUNTIF('Dados Gerais por Municipio'!$L$3:$L$491,'Dados Gerais Resumo Por Área'!B4&" - "&'Dados Gerais Resumo Por Área'!C4) -> 45122.401 | G4: =SUMIF('Dados Gerais por Municipio'!$L$3:$L$491,'Dados Gerais Resumo Por Área'!B4&" - "&'Dados Gerais Resumo Por Área'!C4,'Dados Gerais por Municipio'!$F$3:$F$491)/COUNTIF('Dados Gerais por Municipio'!$L$3:$L$491,'Dados Gerais Resumo Por Área'!B4&" - "&'Dados Gerais Resumo Por Área'!C4) -> 0.68486667 | H4: =SUMIF('Dados Gerais por Municipio'!$L$3:$L$491,'Dados Gerais Resumo Por Área'!B4&" - "&'Dados Gerais Resumo Por Área'!C4,'Dados Gerais por Municipio'!$G$3:$G$491)/COUNTIF('Dados Gerais por Municipio'!$L$3:$L$491,'Dados Gerais Resumo Por Área'!B4&" - "&'Dados Gerais Resumo Por Área'!C4) -> 0.70666049
A5: 03 | B5: Leste | C5: A03 | D5: 197.28 | E5: =ROUNDUP(SUMIF('Fator Tráfego (DER-PR)'!$AR$6:$AR$1368,B5&" - "&C5,'Fator Tráfego (DER-PR)'!$AN$6:$AN$1368)/SUMIF('Fator Tráfego (DER-PR)'!$AR$6:$AR$1368,B5&" - "&C5,'Fator Tráfego (DER-PR)'!$J$6:$J$1368),0) -> 4203 | F5: =SUMIF('Dados Gerais por Municipio'!$L$3:$L$491,'Dados Gerais Resumo Por Área'!B5&" - "&'Dados Gerais Resumo Por Área'!C5,'Dados Gerais por Municipio'!$E$3:$E$491)/COUNTIF('Dados Gerais por Municipio'!$L$3:$L$491,'Dados Gerais Resumo Por Área'!B5&" - "&'Dados Gerais Resumo Por Área'!C5) -> 46763.071 | G5: =SUMIF('Dados Gerais por Municipio'!$L$3:$L$491,'Dados Gerais Resumo Por Área'!B5&" - "&'Dados Gerais Resumo Por Área'!C5,'Dados Gerais por Municipio'!$F$3:$F$491)/COUNTIF('Dados Gerais por Municipio'!$L$3:$L$491,'Dados Gerais Resumo Por Área'!B5&" - "&'Dados Gerais Resumo Por Área'!C5) -> 0.69790909 | H5: =SUMIF('Dados Gerais por Municipio'!$L$3:$L$491,'Dados Gerais Resumo Por Área'!B5&" - "&'Dados Gerais Resumo Por Área'!C5,'Dados Gerais por Municipio'!$G$3:$G$491)/COUNTIF('Dados Gerais por Municipio'!$L$3:$L$491,'Dados Gerais Resumo Por Área'!B5&" - "&'Dados Gerais Resumo Por Área'!C5) -> 0.7170576
A6: 04 | B6: Leste | C6: A04 | D6: 255.87 | E6: =ROUNDUP(SUMIF('Fator Tráfego (DER-PR)'!$AR$6:$AR$1368,B6&" - "&C6,'Fator Tráfego (DER-PR)'!$AN$6:$AN$1368)/SUMIF('Fator Tráfego (DER-PR)'!$AR$6:$AR$1368,B6&" - "&C6,'Fator Tráfego (DER-PR)'!$J$6:$J$1368),0) -> 3408 | F6: =SUMIF('Dados Gerais por Municipio'!$L$3:$L$491,'Dados Gerais Resumo Por Área'!B6&" - "&'Dados Gerais Resumo Por Área'!C6,'Dados Gerais por Municipio'!$E$3:$E$491)/COUNTIF('Dados Gerais por Municipio'!$L$3:$L$491,'Dados Gerais Resumo Por Área'!B6&" - "&'Dados Gerais Resumo Por Área'!C6) -> 55353.041 | G6: =SUMIF('Dados Gerais por Municipio'!$L$3:$L$491,'Dados Gerais Resumo Por Área'!B6&" - "&'Dados Gerais Resumo Por Área'!C6,'Dados Gerais por Municipio'!$F$3:$F$491)/COUNTIF('Dados Gerais por Municipio'!$L$3:$L$491,'Dados Gerais Resumo Por Área'!B6&" - "&'Dados Gerais Resumo Por Área'!C6) -> 0.68885714 | H6: =SUMIF('Dados Gerais por Municipio'!$L$3:$L$491,'Dados Gerais Resumo Por Área'!B6&" - "&'Dados Gerais Resumo Por Área'!C6,'Dados Gerais por Municipio'!$G$3:$G$491)/COUNTIF('Dados Gerais por Municipio'!$L$3:$L$491,'Dados Gerais Resumo Por Área'!B6&" - "&'Dados Gerais Resumo Por Área'!C6) -> 0.74339525
A7: 05 | B7: Leste | C7: A05 | D7: 297.7 | E7: =ROUNDUP(SUMIF('Fator Tráfego (DER-PR)'!$AR$6:$AR$1368,B7&" - "&C7,'Fator Tráfego (DER-PR)'!$AN$6:$AN$1368)/SUMIF('Fator Tráfego (DER-PR)'!$AR$6:$AR$1368,B7&" - "&C7,'Fator Tráfego (DER-PR)'!$J$6:$J$1368),0) -> 3447 | F7: =SUMIF('Dados Gerais por Municipio'!$L$3:$L$491,'Dados Gerais Resumo Por Área'!B7&" - "&'Dados Gerais Resumo Por Área'!C7,'Dados Gerais por Municipio'!$E$3:$E$491)/COUNTIF('Dados Gerais por Municipio'!$L$3:$L$491,'Dados Gerais Resumo Por Área'!B7&" - "&'Dados Gerais Resumo Por Área'!C7) -> 47291.82 | G7: =SUMIF('Dados Gerais por Municipio'!$L$3:$L$491,'Dados Gerais Resumo Por Área'!B7&" - "&'Dados Gerais Resumo Por Área'!C7,'Dados Gerais por Municipio'!$F$3:$F$491)/COUNTIF('Dados Gerais por Municipio'!$L$3:$L$491,'Dados Gerais Resumo Por Área'!B7&" - "&'Dados Gerais Resumo Por Área'!C7) -> 0.686625 | H7: =SUMIF('Dados Gerais por Municipio'!$L$3:$L$491,'Dados Gerais Resumo Por Área'!B7&" - "&'Dados Gerais Resumo Por Área'!C7,'Dados Gerais por Municipio'!$G$3:$G$491)/COUNTIF('Dados Gerais por Municipio'!$L$3:$L$491,'Dados Gerais Resumo Por Área'!B7&" - "&'Dados Gerais Resumo Por Área'!C7) -> 0.73063399
A8: 06 | B8: Campos Gerais | C8: A01 | D8: 305.15 | E8: =ROUNDUP(SUMIF('Fator Tráfego (DER-PR)'!$AR$6:$AR$1368,B8&" - "&C8,'Fator Tráfego (DER-PR)'!$AN$6:$AN$1368)/SUMIF('Fator Tráfego (DER-PR)'!$AR$6:$AR$1368,B8&" - "&C8,'Fator Tráfego (DER-PR)'!$J$6:$J$1368),0) -> 2462 | F8: =SUMIF('Dados Gerais por Municipio'!$L$3:$L$491,'Dados Gerais Resumo Por Área'!B8&" - "&'Dados Gerais Resumo Por Área'!C8,'Dados Gerais por Municipio'!$E$3:$E$491)/COUNTIF('Dados Gerais por Municipio'!$L$3:$L$491,'Dados Gerais Resumo Por Área'!B8&" - "&'Dados Gerais Resumo Por Área'!C8) -> 45972.794 | G8: =SUMIF('Dados Gerais por Municipio'!$L$3:$L$491,'Dados Gerais Resumo Por Área'!B8&" - "&'Dados Gerais Resumo Por Área'!C8,'Dados Gerais por Municipio'!$F$3:$F$491)/COUNTIF('Dados Gerais por Municipio'!$L$3:$L$491,'Dados Gerais Resumo Por Área'!B8&" - "&'Dados Gerais Resumo Por Área'!C8) -> 0.6939 | H8: =SUMIF('Dados Gerais por Municipio'!$L$3:$L$491,'Dados Gerais Resumo Por Área'!B8&" - "&'Dados Gerais Resumo Por Área'!C8,'Dados Gerais por Municipio'!$G$3:$G$491)/COUNTIF('Dados Gerais por Municipio'!$L$3:$L$491,'Dados Gerais Resumo Por Área'!B8&" - "&'Dados Gerais Resumo Por Área'!C8) -> 0.74846373
A9: 07 | B9: Campos Gerais | C9: A02 | D9: 287.51 | E9: =ROUNDUP(SUMIF('Fator Tráfego (DER-PR)'!$AR$6:$AR$1368,B9&" - "&C9,'Fator Tráfego (DER-PR)'!$AN$6:$AN$1368)/SUMIF('Fator Tráfego (DER-PR)'!$AR$6:$AR$1368,B9&" - "&C9,'Fator Tráfego (DER-PR)'!$J$6:$J$1368),0) -> 2750 | F9: =SUMIF('Dados Gerais por Municipio'!$L$3:$L$491,'Dados Gerais Resumo Por Área'!B9&" - "&'Dados Gerais Resumo Por Área'!C9,'Dados Gerais por Municipio'!$E$3:$E$491)/COUNTIF('Dados Gerais por Municipio'!$L$3:$L$491,'Dados Gerais Resumo Por Área'!B9&" - "&'Dados Gerais Resumo Por Área'!C9) -> 64643.592 | G9: =SUMIF('Dados Gerais por Municipio'!$L$3:$L$491,'Dados Gerais Resumo Por Área'!B9&" - "&'Dados Gerais Resumo Por Área'!C9,'Dados Gerais por Municipio'!$F$3:$F$491)/COUNTIF('Dados Gerais por Municipio'!$L$3:$L$491,'Dados Gerais Resumo Por Área'!B9&" - "&'Dados Gerais Resumo Por Área'!C9) -> 0.7186 | H9: =SUMIF('Dados Gerais por Municipio'!$L$3:$L$491,'Dados Gerais Resumo Por Área'!B9&" - "&'Dados Gerais Resumo Por Área'!C9,'Dados Gerais por Municipio'!$G$3:$G$491)/COUNTIF('Dados Gerais por Municipio'!$L$3:$L$491,'Dados Gerais Resumo Por Área'!B9&" - "&'Dados Gerais Resumo Por Área'!C9) -> 0.77188989
A10: 08 | B10: Campos Gerais | C10: A03 | D10: 315.48 | E10: =ROUNDUP(SUMIF('Fator Tráfego (DER-PR)'!$AR$6:$AR$1368,B10&" - "&C10,'Fator Tráfego (DER-PR)'!$AN$6:$AN$1368)/SUMIF('Fator Tráfego (DER-PR)'!$AR$6:$AR$1368,B10&" - "&C10,'Fator Tráfego (DER-PR)'!$J$6:$J$1368),0) -> 2547 | F10: =SUMIF('Dados Gerais por Municipio'!$L$3:$L$491,'Dados Gerais Resumo Por Área'!B10&" - "&'Dados Gerais Resumo Por Área'!C10,'Dados Gerais por Municipio'!$E$3:$E$491)/COUNTIF('Dados Gerais por Municipio'!$L$3:$L$491,'Dados Gerais Resumo Por Área'!B10&" - "&'Dados Gerais Resumo Por Área'!C10) -> 46851.221 | G10: =SUMIF('Dados Gerais por Municipio'!$L$3:$L$491,'Dados Gerais Resumo Por Área'!B10&" - "&'Dados Gerais Resumo Por Área'!C10,'Dados Gerais por Municipio'!$F$3:$F$491)/COUNTIF('Dados Gerais por Municipio'!$L$3:$L$491,'Dados Gerais Resumo Por Área'!B10&" - "&'Dados Gerais Resumo Por Área'!C10) -> 0.65177778 | H10: =SUMIF('Dados Gerais por Municipio'!$L$3:$L$491,'Dados Gerais Resumo Por Área'!B10&" - "&'Dados Gerais Resumo Por Área'!C10,'Dados Gerais por Municipio'!$G$3:$G$491)/COUNTIF('Dados Gerais por Municipio'!$L$3:$L$491,'Dados Gerais Resumo Por Área'!B10&" - "&'Dados Gerais Resumo Por Área'!C10) -> 0.7028867
A11: 09 | B11: Campos Gerais | C11: A04 | D11: 290.73 | E11: =ROUNDUP(SUMIF('Fator Tráfego (DER-PR)'!$AR$6:$AR$1368,B11&" - "&C11,'Fator Tráfego (DER-PR)'!$AN$6:$AN$1368)/SUMIF('Fator Tráfego (DER-PR)'!$AR$6:$AR$1368,B11&" - "&C11,'Fator Tráfego (DER-PR)'!$J$6:$J$1368),0) -> 2065 | F11: =SUMIF('Dados Gerais por Municipio'!$L$3:$L$491,'Dados Gerais Resumo Por Área'!B11&" - "&'Dados Gerais Resumo Por Área'!C11,'Dados Gerais por Municipio'!$E$3:$E$491)/COUNTIF('Dados Gerais por Municipio'!$L$3:$L$491,'Dados Gerais Resumo Por Área'!B11&" - "&'Dados Gerais Resumo Por Área'!C11) -> 47141.524 | G11: =SUMIF('Dados Gerais por Municipio'!$L$3:$L$491,'Dados Gerais Resumo Por Área'!B11&" - "&'Dados Gerais Resumo Por Área'!C11,'Dados Gerais por Municipio'!$F$3:$F$491)/COUNTIF('Dados Gerais por Municipio'!$L$3:$L$491,'Dados Gerais Resumo Por Área'!B11&" - "&'Dados Gerais Resumo Por Área'!C11) -> 0.67016667 | H11: =SUMIF('Dados Gerais por Municipio'!$L$3:$L$491,'Dados Gerais Resumo Por Área'!B11&" - "&'Dados Gerais Resumo Por Área'!C11,'Dados Gerais por Municipio'!$G$3:$G$491)/COUNTIF('Dados Gerais por Municipio'!$L$3:$L$491,'Dados Gerais Resumo Por Área'!B11&" - "&'Dados Gerais Resumo Por Área'!C11) -> 0.74957761
A12: 10 | B12: Campos Gerais | C12: A05 | D12: 383.01 | E12: =ROUNDUP(SUMIF('Fator Tráfego (DER-PR)'!$AR$6:$AR$1368,B12&" - "&C12,'Fator Tráfego (DER-PR)'!$AN$6:$AN$1368)/SUMIF('Fator Tráfego (DER-PR)'!$AR$6:$AR$1368,B12&" - "&C12,'Fator Tráfego (DER-PR)'!$J$6:$J$1368),0) -> 3388 | F12: =SUMIF('Dados Gerais por Municipio'!$L$3:$L$491,'Dados Gerais Resumo Por Área'!B12&" - "&'Dados Gerais Resumo Por Área'!C12,'Dados Gerais por Municipio'!$E$3:$E$491)/COUNTIF('Dados Gerais por Municipio'!$L$3:$L$491,'Dados Gerais Resumo Por Área'!B12&" - "&'Dados Gerais Resumo Por Área'!C12) -> 49309.042 | G12: =SUMIF('Dados Gerais por Municipio'!$L$3:$L$491,'Dados Gerais Resumo Por Área'!B12&" - "&'Dados Gerais Resumo Por Área'!C12,'Dados Gerais por Municipio'!$F$3:$F$491)/COUNTIF('Dados Gerais por Municipio'!$L$3:$L$491,'Dados Gerais Resumo Por Área'!B12&" - "&'Dados Gerais Resumo Por Área'!C12) -> 0.65609091 | H12: =SUMIF('Dados Gerais por Municipio'!$L$3:$L$491,'Dados Gerais Resumo Por Área'!B12&" - "&'Dados Gerais Resumo Por Área'!C12,'Dados Gerais por Municipio'!$G$3:$G$491)/COUNTIF('Dados Gerais por Municipio'!$L$3:$L$491,'Dados Gerais Resumo Por Área'!B12&" - "&'Dados Gerais Resumo Por Área'!C12) -> 0.73447934
A13: 11 | B13: Campos Gerais | C13: A06 | D13: 326.22 | E13: =ROUNDUP(SUMIF('Fator Tráfego (DER-PR)'!$AR$6:$AR$1368,B13&" - "&C13,'Fator Tráfego (DER-PR)'!$AN$6:$AN$1368)/SUMIF('Fator Tráfego (DER-PR)'!$AR$6:$AR$1368,B13&" - "&C13,'Fator Tráfego (DER-PR)'!$J$6:$J$1368),0) -> 1839 | F13: =SUMIF('Dados Gerais por Municipio'!$L$3:$L$491,'Dados Gerais Resumo Por Área'!B13&" - "&'Dados Gerais Resumo Por Área'!C13,'Dados Gerais por Municipio'!$E$3:$E$491)/COUNTIF('Dados Gerais por Municipio'!$L$3:$L$491,'Dados Gerais Resumo Por Área'!B13&" - "&'Dados Gerais Resumo Por Área'!C13) -> 38705.772 | G13: =SUMIF('Dados Gerais por Municipio'!$L$3:$L$491,'Dados Gerais Resumo Por Área'!B13&" - "&'Dados Gerais Resumo Por Área'!C13,'Dados Gerais por Municipio'!$F$3:$F$491)/COUNTIF('Dados Gerais por Municipio'!$L$3:$L$491,'Dados Gerais Resumo Por Área'!B13&" - "&'Dados Gerais Resumo Por Área'!C13) -> 0.6509 | H13: =SUMIF('Dados Gerais por Municipio'!$L$3:$L$491,'Dados Gerais Resumo Por Área'!B13&" - "&'Dados Gerais Resumo Por Área'!C13,'Dados Gerais por Municipio'!$G$3:$G$491)/COUNTIF('Dados Gerais por Municipio'!$L$3:$L$491,'Dados Gerais Resumo Por Área'!B13&" - "&'Dados Gerais Resumo Por Área'!C13) -> 0.7007629
A14: 12 | B14: Campos Gerais | C14: A07 | D14: 192.14 | E14: =ROUNDUP(SUMIF('Fator Tráfego (DER-PR)'!$AR$6:$AR$1368,B14&" - "&C14,'Fator Tráfego (DER-PR)'!$AN$6:$AN$1368)/SUMIF('Fator Tráfego (DER-PR)'!$AR$6:$AR$1368,B14&" - "&C14,'Fator Tráfego (DER-PR)'!$J$6:$J$1368),0) -> 2586 | F14: =SUMIF('Dados Gerais por Municipio'!$L$3:$L$491,'Dados Gerais Resumo Por Área'!B14&" - "&'Dados Gerais Resumo Por Área'!C14,'Dados Gerais por Municipio'!$E$3:$E$491)/COUNTIF('Dados Gerais por Municipio'!$L$3:$L$491,'Dados Gerais Resumo Por Área'!B14&" - "&'Dados Gerais Resumo Por Área'!C14) -> 46524.092 | G14: =SUMIF('Dados Gerais por Municipio'!$L$3:$L$491,'Dados Gerais Resumo Por Área'!B14&" - "&'Dados Gerais Resumo Por Área'!C14,'Dados Gerais por Municipio'!$F$3:$F$491)/COUNTIF('Dados Gerais por Municipio'!$L$3:$L$491,'Dados Gerais Resumo Por Área'!B14&" - "&'Dados Gerais Resumo Por Área'!C14) -> 0.6564 | H14: =SUMIF('Dados Gerais por Municipio'!$L$3:$L$491,'Dados Gerais Resumo Por Área'!B14&" - "&'Dados Gerais Resumo Por Área'!C14,'Dados Gerais por Municipio'!$G$3:$G$491)/COUNTIF('Dados Gerais por Municipio'!$L$3:$L$491,'Dados Gerais Resumo Por Área'!B14&" - "&'Dados Gerais Resumo Por Área'!C14) -> 0.72191773
... A42: 40 | B42: Oeste | C42: A08 | D42: 306.38 | E42: =ROUNDUP(SUMIF('Fator Tráfego (DER-PR)'!$AR$6:$AR$1368,B42&" - "&C42,'Fator Tráfego (DER-PR)'!$AN$6:$AN$1368)/SUMIF('Fator Tráfego (DER-PR)'!$AR$6:$AR$1368,B42&" - "&C42,'Fator Tráfego (DER-PR)'!$J$6:$J$1368),0) -> 2294 | F42: =SUMIF('Dados Gerais por Municipio'!$L$3:$L$491,'Dados Gerais Resumo Por Área'!B42&" - "&'Dados Gerais Resumo Por Área'!C42,'Dados Gerais por Municipio'!$E$3:$E$491)/COUNTIF('Dados Gerais por Municipio'!$L$3:$L$491,'Dados Gerais Resumo Por Área'!B42&" - "&'Dados Gerais Resumo Por Área'!C42) -> 66526.306 | G42: =SUMIF('Dados Gerais por Municipio'!$L$3:$L$491,'Dados Gerais Resumo Por Área'!B42&" - "&'Dados Gerais Resumo Por Área'!C42,'Dados Gerais por Municipio'!$F$3:$F$491)/COUNTIF('Dados Gerais por Municipio'!$L$3:$L$491,'Dados Gerais Resumo Por Área'!B42&" - "&'Dados Gerais Resumo Por Área'!C42) -> 0.697 | H42: =SUMIF('Dados Gerais por Municipio'!$L$3:$L$491,'Dados Gerais Resumo Por Área'!B42&" - "&'Dados Gerais Resumo Por Área'!C42,'Dados Gerais por Municipio'!$G$3:$G$491)/COUNTIF('Dados Gerais por Municipio'!$L$3:$L$491,'Dados Gerais Resumo Por Área'!B42&" - "&'Dados Gerais Resumo Por Área'!C42) -> 0.7436744
D43: =SUM(D3:D42) -> 10974.18
B45: Sistema Rodoviário 2022
B46: Ext. Pavimenta + Não Pavimentada
B47: SR | C47: Ext (km) | D47: %
B48: Leste | C48: =SUM(D3:D7) -> 1188.92 | D48: =C48/$C$53 -> 0.10833794
B49: Campos Gerais | C49: =SUM(D8:D14) -> 2100.24 | D49: =C49/$C$53 -> 0.19138013
B50: Norte | C50: =SUM(D15:D24) -> 2280.77 | D50: =C50/$C$53 -> 0.20783056
B51: Noroeste | C51: =SUM(D25:D34) -> 3040.87 | D51: =C51/$C$53 -> 0.27709314
B52: Oeste | C52: =SUM(D35:D42) -> 2363.38 | D52: =C52/$C$53 -> 0.21535823
B53: Total | C53: =SUM(C48:C52) -> 10974.18
B54: Extensão Pavimentada
B55: SR | C55: Ext (km) | D55: %
B56: Leste | C56: =SUM('[1]Adm e Canteiro ADM'!$D$6:$D$10) -> 768.65 | D56: =C56/$C$61 -> 0.079137839
B57: Campos Gerais | C57: =SUM('[1]Adm e Canteiro ADM'!$D$11:$D$17) -> 1686.65 | D57: =C57/$C$61 -> 0.17365229
B58: Norte | C58: =SUM('[1]Adm e Canteiro ADM'!$D$18:$D$27) -> 2034.42 | D58: =C58/$C$61 -> 0.20945762
B59: Noroeste | C59: =SUM('[1]Adm e Canteiro ADM'!$D$28:$D$37) -> 2955.81 | D59: =C59/$C$61 -> 0.3043211
B60: Oeste | C60: =SUM('[1]Adm e Canteiro ADM'!$D$38:$D$45) -> 2267.27 | D60: =C60/$C$61 -> 0.23343114
B61: Total | C61: =SUM(C56:C60) -> 9712.8

Sheet Dados Gerais Resumo PorSR
A1: Fator Tráfego por Sup. Regional
A2: SR | B2: Sup. Regional | C2: Áreas | D2: Ext. (km) | E2: Fator de Tráfego Média TMDA
A3: 1 | B3: Leste | C3: 5 | D3: =SUM('Dados Gerais Resumo Por Área'!D3:D7) -> 1188.92 | E3: =ROUNDUP(SUMIF('Fator Tráfego (DER-PR)'!$AQ$6:$AQ$1368,B3,'Fator Tráfego (DER-PR)'!$AN$6:$AN$1368)/SUMIF('Fator Tráfego (DER-PR)'!$AQ$6:$AQ$1368,B3,'Fator Tráfego (DER-PR)'!$J$6:$J$1368),0) -> 4059
A4: 2 | B4: Campos Gerais | C4: 7 | D4: =SUM('Dados Gerais Resumo Por Área'!D8:D14) -> 2100.24 | E4: =ROUNDUP(SUMIF('Fator Tráfego (DER-PR)'!$AQ$6:$AQ$1368,B4,'Fator Tráfego (DER-PR)'!$AN$6:$AN$1368)/SUMIF('Fator Tráfego (DER-PR)'!$AQ$6:$AQ$1368,B4,'Fator Tráfego (DER-PR)'!$J$6:$J$1368),0) -> 2544
A5: 3 | B5: Norte | C5: 10 | D5: =SUM('Dados Gerais Resumo Por Área'!D15:D24) -> 2280.77 | E5: =ROUNDUP(SUMIF('Fator Tráfego (DER-PR)'!$AQ$6:$AQ$1368,B5,'Fator Tráfego (DER-PR)'!$AN$6:$AN$1368)/SUMIF('Fator Tráfego (DER-PR)'!$AQ$6:$AQ$1368,B5,'Fator Tráfego (DER-PR)'!$J$6:$J$1368),0) -> 2183
A6: 4 | B6: Noroeste | C6: 10 | D6: =SUM('Dados Gerais Resumo Por Área'!D25:D34) -> 3040.87 | E6: =ROUNDUP(SUMIF('Fator Tráfego (DER-PR)'!$AQ$6:$AQ$1368,B6,'Fator Tráfego (DER-PR)'!$AN$6:$AN$1368)/SUMIF('Fator Tráfego (DER-PR)'!$AQ$6:$AQ$1368,B6,'Fator Tráfego (DER-PR)'!$J$6:$J$1368),0) -> 1744
A7: 5 | B7: Oeste | C7: 8 | D7: =SUM('Dados Gerais Resumo Por Área'!D35:D42) -> 2363.38 | E7: =ROUNDUP(SUMIF('Fator Tráfego (DER-PR)'!$AQ$6:$AQ$1368,B7,'Fator Tráfego (DER-PR)'!$AN$6:$AN$1368)/SUMIF('Fator Tráfego (DER-PR)'!$AQ$6:$AQ$1368,B7,'Fator Tráfego (DER-PR)'!$J$6:$J$1368),0) -> 1916
C8: =SUM(C3:C7) -> 40 | D8: =SUM(D3:D7) -> 10974.18
A10: *TMDA - Tráfego Médio Diário Anual
B12: Sistema Rodoviário 2022
B13: Ext. Pavimenta + Não Pavimentada
B14: SR | C14: Ext (km) | D14: %
B15: Leste | C15: =SUM(D3:D3) -> 1188.92 | D15: =C15/$C$20 -> 0.10833794
B16: Campos Gerais | C16: =SUM(D4:D4) -> 2100.24 | D16: =C16/$C$20 -> 0.19138013
B17: Norte | C17: =SUM(D5:D5) -> 2280.77 | D17: =C17/$C$20 -> 0.20783056
B18: Noroeste | C18: =SUM(D6:D6) -> 3040.87 | D18: =C18/$C$20 -> 0.27709314
B19: Oeste | C19: =SUM(D7:D7) -> 2363.38 | D19: =C19/$C$20 -> 0.21535823
B20: Total | C20: =SUM(C15:C19) -> 10974.18
B21: Extensão Pavimentada
B22: SR | C22: Ext (km) | D22: %
B23: Leste | C23: =SUM('[1]Adm e Canteiro ADM'!$D$6:$D$10) -> 768.65 | D23: =C23/$C$28 -> 0.079137839
B24: Campos Gerais | C24: =SUM('[1]Adm e Canteiro ADM'!$D$11:$D$17) -> 1686.65 | D24: =C24/$C$28 -> 0.17365229
B25: Norte | C25: =SUM('[1]Adm e Canteiro ADM'!$D$18:$D$27) -> 2034.42 | D25: =C25/$C$28 -> 0.20945762
B26: Noroeste | C26: =SUM('[1]Adm e Canteiro ADM'!$D$28:$D$37) -> 2955.81 | D26: =C26/$C$28 -> 0.3043211
B27: Oeste | C27: =SUM('[1]Adm e Canteiro ADM'!$D$38:$D$45) -> 2267.27 | D27: =C27/$C$28 -> 0.23343114
B28: Total | C28: =SUM(C23:C27) -> 9712.8

Sheet Dados Gerais por Municipio
A1: LOTE | B1: SUP. REG. | C1: ÁREA | D1: MUNICIPIO | E1: IBGE 2022 | G1: IDPM - Índices Ipardes - 2022
E2: PIB per capita - R$ [2023] | F2: IDHM | G2: IDPM Geral 2022 | H2: IDPM Renda 2022 | I2: IDPM Educação 2022 | J2: IDPM Saúde 2022
A3: LOTE 01 | B3: Leste | C3: A01 | D3: Antonina | E3: =VLOOKUP(D3,'IDHM (IBGE2022)'!$A$4:$N$402,14,FALSE) -> 55368.68 | F3: =VLOOKUP(D3,'IDHM (IBGE2022)'!$A$4:$J$402,10,FALSE) -> 0.687 | G3: =AVERAGE(H3:J3) -> 0.64103441 | H3: =VLOOKUP(D3,'IPDM_renda (IPARDES-PR)'!$A$4:$N$420,14,FALSE) -> 0.47713553 | I3: =VLOOKUP(D3,'IPDM_educação (IPARDES-PR)'!$A$4:$N$420,14,FALSE) -> 0.73349154 | J3: =VLOOKUP(D3,'IPDM_saúde (IPARDES-PR)'!$A$4:$N$466,14,FALSE) -> 0.71247617 | L3: =B3&" - "&C3 -> Leste - A01
A4: LOTE 01 | B4: Leste | C4: A01 | D4: Campina Grande do Sul | E4: =VLOOKUP(D4,'IDHM (IBGE2022)'!$A$4:$N$402,14,FALSE) -> 60047.41 | F4: =VLOOKUP(D4,'IDHM (IBGE2022)'!$A$4:$J$402,10,FALSE) -> 0.718 | G4: =AVERAGE(H4:J4) -> 0.72599707 | H4: =VLOOKUP(D4,'IPDM_renda (IPARDES-PR)'!$A$4:$N$420,14,FALSE) -> 0.5593837 | I4: =VLOOKUP(D4,'IPDM_educação (IPARDES-PR)'!$A$4:$N$420,14,FALSE) -> 0.8948303 | J4: =VLOOKUP(D4,'IPDM_saúde (IPARDES-PR)'!$A$4:$N$466,14,FALSE) -> 0.72377723 | L4: =B4&" - "&C4 -> Leste - A01
A5: LOTE 01 | B5: Leste | C5: A01 | D5: Guaraqueçaba | E5: =VLOOKUP(D5,'IDHM (IBGE2022)'!$A$4:$N$402,14,FALSE) -> 19660.96 | F5: =VLOOKUP(D5,'IDHM (IBGE2022)'!$A$4:$J$402,10,FALSE) -> 0.587 | G5: =AVERAGE(H5:J5) -> 0.57223015 | H5: =VLOOKUP(D5,'IPDM_renda (IPARDES-PR)'!$A$4:$N$420,14,FALSE) -> 0.28092968 | I5: =VLOOKUP(D5,'IPDM_educação (IPARDES-PR)'!$A$4:$N$420,14,FALSE) -> 0.65578528 | J5: =VLOOKUP(D5,'IPDM_saúde (IPARDES-PR)'!$A$4:$N$466,14,FALSE) -> 0.77997548 | L5: =B5&" - "&C5 -> Leste - A01
A6: LOTE 01 | B6: Leste | C6: A01 | D6: Guaratuba | E6: =VLOOKUP(D6,'IDHM (IBGE2022)'!$A$4:$N$402,14,FALSE) -> 29027.37 | F6: =VLOOKUP(D6,'IDHM (IBGE2022)'!$A$4:$J$402,10,FALSE) -> 0.717 | G6: =AVERAGE(H6:J6) -> 0.69331456 | H6: =VLOOKUP(D6,'IPDM_renda (IPARDES-PR)'!$A$4:$N$420,14,FALSE) -> 0.47404357 | I6: =VLOOKUP(D6,'IPDM_educação (IPARDES-PR)'!$A$4:$N$420,14,FALSE) -> 0.87301052 | J6: =VLOOKUP(D6,'IPDM_saúde (IPARDES-PR)'!$A$4:$N$466,14,FALSE) -> 0.73288959 | L6: =B6&" - "&C6 -> Leste - A01
A7: LOTE 01 | B7: Leste | C7: A01 | D7: Matinhos | E7: =VLOOKUP(D7,'IDHM (IBGE2022)'!$A$4:$N$402,14,FALSE) -> 29246.91 | F7: =VLOOKUP(D7,'IDHM (IBGE2022)'!$A$4:$J$402,10,FALSE) -> 0.743 | G7: =AVERAGE(H7:J7) -> 0.66679244 | H7: =VLOOKUP(D7,'IPDM_renda (IPARDES-PR)'!$A$4:$N$420,14,FALSE) -> 0.45236685 | I7: =VLOOKUP(D7,'IPDM_educação (IPARDES-PR)'!$A$4:$N$420,14,FALSE) -> 0.92436497 | J7: =VLOOKUP(D7,'IPDM_saúde (IPARDES-PR)'!$A$4:$N$466,14,FALSE) -> 0.62364549 | L7: =B7&" - "&C7 -> Leste - A01
A8: LOTE 01 | B8: Leste | C8: A01 | D8: Morretes | E8: =VLOOKUP(D8,'IDHM (IBGE2022)'!$A$4:$N$402,14,FALSE) -> 29204.87 | F8: =VLOOKUP(D8,'IDHM (IBGE2022)'!$A$4:$J$402,10,FALSE) -> 0.686 | G8: =AVERAGE(H8:J8) -> 0.60184614 | H8: =VLOOKUP(D8,'IPDM_renda (IPARDES-PR)'!$A$4:$N$420,14,FALSE) -> 0.45956605 | I8: =VLOOKUP(D8,'IPDM_educação (IPARDES-PR)'!$A$4:$N$420,14,FALSE) -> 0.77996942 | J8: =VLOOKUP(D8,'IPDM_saúde (IPARDES-PR)'!$A$4:$N$466,14,FALSE) -> 0.56600296 | L8: =B8&" - "&C8 -> Leste - A01
A9: LOTE 01 | B9: Leste | C9: A01 | D9: Pontal do Paraná | E9: =VLOOKUP(D9,'IDHM (IBGE2022)'!$A$4:$N$402,14,FALSE) -> 26613.26 | F9: =VLOOKUP(D9,'IDHM (IBGE2022)'!$A$4:$J$402,10,FALSE) -> 0.738 | G9: =AVERAGE(H9:J9) -> 0.62137824 | H9: =VLOOKUP(D9,'IPDM_renda (IPARDES-PR)'!$A$4:$N$420,14,FALSE) -> 0.44671276 | I9: =VLOOKUP(D9,'IPDM_educação (IPARDES-PR)'!$A$4:$N$420,14,FALSE) -> 0.87261304 | J9: =VLOOKUP(D9,'IPDM_saúde (IPARDES-PR)'!$A$4:$N$466,14,FALSE) -> 0.5448089 | L9: =B9&" - "&C9 -> Leste - A01
A10: LOTE 01 | B10: Leste | C10: A01 | D10: Quatro Barras | E10: =VLOOKUP(D10,'IDHM (IBGE2022)'!$A$4:$N$402,14,FALSE) -> 96572.32 | F10: =VLOOKUP(D10,'IDHM (IBGE2022)'!$A$4:$J$402,10,FALSE) -> 0.742 | G10: =AVERAGE(H10:J10) -> 0.85472246 | H10: =VLOOKUP(D10,'IPDM_renda (IPARDES-PR)'!$A$4:$N$420,14,FALSE) -> 0.76100353 | I10: =VLOOKUP(D10,'IPDM_educação (IPARDES-PR)'!$A$4:$N$420,14,FALSE) -> 0.91950194 | J10: =VLOOKUP(D10,'IPDM_saúde (IPARDES-PR)'!$A$4:$N$466,14,FALSE) -> 0.8836619 | L10: =B10&" - "&C10 -> Leste - A01
A11: LOTE 02 | B11: Leste | C11: A02 | D11: Almirante Tamandaré | E11: =VLOOKUP(D11,'IDHM (IBGE2022)'!$A$4:$N$402,14,FALSE) -> 18715.79 | F11: =VLOOKUP(D11,'IDHM (IBGE2022)'!$A$4:$J$402,10,FALSE) -> 0.699 | G11: =AVERAGE(H11:J11) -> 0.62592222 | H11: =VLOOKUP(D11,'IPDM_renda (IPARDES-PR)'!$A$4:$N$420,14,FALSE) -> 0.42379101 | I11: =VLOOKUP(D11,'IPDM_educação (IPARDES-PR)'!$A$4:$N$420,14,FALSE) -> 0.65513361 | J11: =VLOOKUP(D11,'IPDM_saúde (IPARDES-PR)'!$A$4:$N$466,14,FALSE) -> 0.79884205 | L11: =B11&" - "&C11 -> Leste - A02
A12: LOTE 02 | B12: Leste | C12: A02 | D12: Bocaiúva do Sul | E12: =VLOOKUP(D12,'IDHM (IBGE2022)'!$A$4:$N$402,14,FALSE) -> 22971.54 | F12: =VLOOKUP(D12,'IDHM (IBGE2022)'!$A$4:$J$402,10,FALSE) -> 0.64 | G12: =AVERAGE(H12:J12) -> 0.6369049 | H12: =VLOOKUP(D12,'IPDM_renda (IPARDES-PR)'!$A$4:$N$420,14,FALSE) -> 0.53650163 | I12: =VLOOKUP(D12,'IPDM_educação (IPARDES-PR)'!$A$4:$N$420,14,FALSE) -> 0.60176329 | J12: =VLOOKUP(D12,'IPDM_saúde (IPARDES-PR)'!$A$4:$N$466,14,FALSE) -> 0.77244979 | L12: =B12&" - "&C12 -> Leste - A02
A13: LOTE 02 | B13: Leste | C13: A02 | D13: Campina Grande do Sul | E13: =VLOOKUP(D13,'IDHM (IBGE2022)'!$A$4:$N$402,14,FALSE) -> 60047.41 | F13: =VLOOKUP(D13,'IDHM (IBGE2022)'!$A$4:$J$402,10,FALSE) -> 0.718 | G13: =AVERAGE(H13:J13) -> 0.72599707 | H13: =VLOOKUP(D13,'IPDM_renda (IPARDES-PR)'!$A$4:$N$420,14,FALSE) -> 0.5593837 | I13: =VLOOKUP(D13,'IPDM_educação (IPARDES-PR)'!$A$4:$N$420,14,FALSE) -> 0.8948303 | J13: =VLOOKUP(D13,'IPDM_saúde (IPARDES-PR)'!$A$4:$N$466,14,FALSE) -> 0.72377723 | L13: =B13&" - "&C13 -> Leste - A02
A14: LOTE 02 | B14: Leste | C14: A02 | D14: Cerro Azul | E14: =VLOOKUP(D14,'IDHM (IBGE2022)'!$A$4:$N$402,14,FALSE) -> 23181.48 | F14: =VLOOKUP(D14,'IDHM (IBGE2022)'!$A$4:$J$402,10,FALSE) -> 0.573 | G14: =AVERAGE(H14:J14) -> 0.62008672 | H14: =VLOOKUP(D14,'IPDM_renda (IPARDES-PR)'!$A$4:$N$420,14,FALSE) -> 0.4151293 | I14: =VLOOKUP(D14,'IPDM_educação (IPARDES-PR)'!$A$4:$N$420,14,FALSE) -> 0.62443495 | J14: =VLOOKUP(D14,'IPDM_saúde (IPARDES-PR)'!$A$4:$N$466,14,FALSE) -> 0.82069592 | L14: =B14&" - "&C14 -> Leste - A02
... A491: LOTE 40 | B491: Oeste | C491: A08 | D491: Vitorino | E491: =VLOOKUP(D491,'IDHM (IBGE2022)'!$A$4:$N$402,14,FALSE) -> 65013.87 | F491: =VLOOKUP(D491,'IDHM (IBGE2022)'!$A$4:$J$402,10,FALSE) -> 0.702 | G491: =AVERAGE(H491:J491) -> 0.71694384 | H491: =VLOOKUP(D491,'IPDM_renda (IPARDES-PR)'!$A$4:$N$420,14,FALSE) -> 0.52482725 | I491: =VLOOKUP(D491,'IPDM_educação (IPARDES-PR)'!$A$4:$N$420,14,FALSE) -> 0.77299839 | J491: =VLOOKUP(D491,'IPDM_saúde (IPARDES-PR)'!$A$4:$N$466,14,FALSE) -> 0.85300587 | L491: =B491&" - "&C491 -> Oeste - A08

Sheet Fator Tráfego (DER-PR)
A2: PLANILHA GERAL (PRs + MUN) | P2: caracaterísticas geométricas
AO4: =ROUNDUP(AN1371/J1371,0) -> 2199
A5: Trecho | H5: DE | I5: PARA | J5: Ext. (km) | K5: Área Gestão | L5: SR | M5: Lotes Conserva | N5: Obs | O5: LOTE | P5: Sit | Q5: Base | R5: Revestimento | S5: Largura | T5: Acostamento | U5: 3ª Faixa | V5: TMDA | W5: 1 | X5: 2 | Y5: 3 | Z5: 4 | AA5: 5 | AE5: 1 | AF5: 2 | AG5: 3 | AH5: 4 | AI5: 5 | AN5: TMDA x Ext. (km)
A6: 082S0090EPR | B6: 082S0090 | C6: 082 | D6: 0090 | E6: 082S | F6: S | G6: 082|0090 | H6: ROSÁRIO DO IVAÍ | I6: ENTR. PR-535 (P/ RIO BRANCO DO IVAÍ) | J6: 18 | K6: A10 | L6: DER SR3 | O6: 22 | P6: PAV | Q6: MH | R6: PMF | S6: 6.2 | T6: 0.5 | U6: 0 | V6: 1080 | W6: 0 | X6: 0 | Y6: 0 | Z6: 18 | AA6: 0 | AB6: =SUM(W6:AA6)-J6 -> 0 | AE6: 0 | AF6: 0 | AG6: 0 | AH6: 18 | AI6: 0 | AJ6: =SUM(AE6:AI6)-J6 -> 0 | AN6: =ROUNDUP(V6*J6,0) -> 19440 | AQ6: Norte | AR6: =AQ6&" - "&K6 -> Norte - A10
A7: 082S0100EPR | B7: 082S0100 | C7: 082 | D7: 0100 | E7: 082S | F7: S | G7: 082|0100 | H7: ENTR. PR-535 (P/ RIO BRANCO DO IVAÍ) | I7: RIBEIRÃO BONITO (A) | J7: 7.53 | K7: A10 | L7: DER SR3 | O7: 22 | P7: PAV | Q7: MH | R7: PMF | S7: 6.2 | T7: 0.5 | U7: 0 | V7: 1080 | W7: 0 | X7: 0 | Y7: 0 | Z7: 7.53 | AA7: 0 | AB7: =SUM(W7:AA7)-J7 -> 0 | AE7: 0 | AF7: 0 | AG7: 0 | AH7: 7.53 | AI7: 0 | AJ7: =SUM(AE7:AI7)-J7 -> 0 | AN7: =ROUNDUP(V7*J7,0) -> 8133 | AQ7: Norte | AR7: =AQ7&" - "&K7 -> Norte - A10
A8: 082M0105MUN | B8: 082M0105 | C8: 082 | D8: 0105 | E8: 082M | F8: M | G8: 082|0105 | H8: RIBEIRÃO BONITO (A) | I8: RIBEIRÃO BONITO (B) | J8: 0.65 | K8: A10 | L8: DER SR3 | O8: 22 | P8: MUN | Q8: MH | R8: PMF | S8: 8.3 | T8: 0 | U8: 0 | V8: 510 | W8: 0 | X8: 0 | Y8: 0 | Z8: 0.65 | AA8: 0 | AB8: =SUM(W8:AA8)-J8 -> 0 | AE8: 0 | AF8: 0 | AG8: 0 | AH8: 0.65 | AI8: 0 | AJ8: =SUM(AE8:AI8)-J8 -> 0 | AN8: =ROUNDUP(V8*J8,0) -> 332 | AQ8: Norte | AR8: =AQ8&" - "&K8 -> Norte - A10
A9: 082S0110EPR | B9: 082S0110 | C9: 082 | D9: 0110 | E9: 082S | F9: S | G9: 082|0110 | H9: RIBEIRÃO BONITO (B) | I9: ENTR. PR-451 (GRANDES RIOS) | J9: 8.12 | K9: A10 | L9: DER SR3 | O9: 22 | P9: PAV | Q9: MH | R9: PMF | S9: 7 | T9: 0.5 | U9: 0 | V9: 1080 | W9: 0 | X9: 0 | Y9: 0 | Z9: 8.12 | AA9: 0 | AB9: =SUM(W9:AA9)-J9 -> 0 | AE9: 0 | AF9: 0 | AG9: 0 | AH9: 8.12 | AI9: 0 | AJ9: =SUM(AE9:AI9)-J9 -> 0 | AN9: =ROUNDUP(V9*J9,0) -> 8770 | AQ9: Norte | AR9: =AQ9&" - "&K9 -> Norte - A10
A10: 082S0150EPR | B10: 082S0150 | C10: 082 | D10: 0150 | E10: 082S | F10: S | G10: 082|0150 | H10: ENTR. PRC-466 (PLACA LUAR) | I10: AC. LUNARDELLI | J10: 10.4 | K10: A07 | L10: DER SR3 | O10: 19 | P10: PAV | Q10: BG | R10: PMF | S10: 7.2 | T10: 1.2 | U10: 0 | V10: 3529 | W10: 0 | X10: 0 | Y10: 0 | Z10: 10.4 | AA10: 0 | AB10: =SUM(W10:AA10)-J10 -> 0 | AE10: 0 | AF10: 0 | AG10: 0 | AH10: 10.4 | AI10: 0 | AJ10: =SUM(AE10:AI10)-J10 -> 0 | AN10: =ROUNDUP(V10*J10,0) -> 36702 | AQ10: Norte | AR10: =AQ10&" - "&K10 -> Norte - A07
A11: 082S0160EPR | B11: 082S0160 | C11: 082 | D11: 0160 | E11: 082S | F11: S | G11: 082|0160 | H11: AC. LUNARDELLI | I11: ENTR. PR-650 (SÃO JOÃO DO IVAÍ) | J11: 14.48 | K11: A07 | L11: DER SR3 | O11: 19 | P11: PAV | Q11: BG | R11: PMF | S11: 7.3 | T11: 1.2 | U11: 0 | V11: 3176 | W11: 0 | X11: 0 | Y11: 0 | Z11: 14.48 | AA11: 0 | AB11: =SUM(W11:AA11)-J11 -> 0 | AE11: 0 | AF11: 0 | AG11: 0 | AH11: 14.48 | AI11: 0 | AJ11: =SUM(AE11:AI11)-J11 -> 0 | AN11: =ROUNDUP(V11*J11,0) -> 45989 | AQ11: Norte | AR11: =AQ11&" - "&K11 -> Norte - A07
A12: 082S0170EPR | B12: 082S0170 | C12: 082 | D12: 0170 | E12: 082S | F12: S | G12: 082|0170 | H12: ENTR. PR-650 (SÃO JOÃO DO IVAÍ) | I12: ENTR. PR-457 (P/ S. PEDRO DO IVAÍ) | J12: 6.46 | K12: A07 | L12: DER SR3 | O12: 19 | P12: PAV | Q12: BG | R12: PMF | S12: 7.2 | T12: 1.2 | U12: 0.4 | V12: 3176 | W12: 0 | X12: 1 | Y12: 0 | Z12: 5.46 | AA12: 0 | AB12: =SUM(W12:AA12)-J12 -> 0 | AE12: 0 | AF12: 1 | AG12: 0 | AH12: 5.46 | AI12: 0 | AJ12: =SUM(AE12:AI12)-J12 -> 0 | AN12: =ROUNDUP(V12*J12,0) -> 20517 | AQ12: Norte | AR12: =AQ12&" - "&K12 -> Norte - A07
A13: 082S0190EPR | B13: 082S0190 | C13: 082 | D13: 0190 | E13: 082S | F13: S | G13: 082|0190 | H13: ENTR. PR-457 (P/ S. PEDRO DO IVAÍ) | I13: ACESSO A LUAR | J13: 6.58 | K13: A07 | L13: DER SR3 | O13: 19 | P13: PAV | Q13: BG | R13: TST | S13: 7.2 | T13: 1.2 | U13: 0 | V13: 2549 | W13: 0 | X13: 1 | Y13: 2 | Z13: 3.58 | AA13: 0 | AB13: =SUM(W13:AA13)-J13 -> 0 | AE13: 0 | AF13: 1 | AG13: 2 | AH13: 3.58 | AI13: 0 | AJ13: =SUM(AE13:AI13)-J13 -> 0 | AN13: =ROUNDUP(V13*J13,0) -> 16773 | AQ13: Norte | AR13: =AQ13&" - "&K13 -> Norte - A07
A14: 082S0195EPR | B14: 082S0195 | C14: 082 | D14: 0195 | E14: 082S | F14: S | G14: 082|0195 | H14: ACESSO A LUAR | I14: RIO CORUMBATAÍ | J14: 5 | K14: A07 | L14: DER SR3 | O14: 19 | P14: PAV | Q14: BG | R14: TST | S14: 7.2 | T14: 1.2 | U14: 0 | V14: 2549 | W14: 0 | X14: 1 | Y14: 0 | Z14: 4 | AA14: 0 | AB14: =SUM(W14:AA14)-J14 -> 0 | AE14: 0 | AF14: 1 | AG14: 0 | AH14: 4 | AI14: 0 | AJ14: =SUM(AE14:AI14)-J14 -> 0 | AN14: =ROUNDUP(V14*J14,0) -> 12745 | AQ14: Norte | AR14: =AQ14&" - "&K14 -> Norte - A07
A15: 082S0200EPR | B15: 082S0200 | C15: 082 | D15: 0200 | E15: 082S | F15: S | G15: 082|0200 | H15: RIO CORUMBATAÍ | I15: ENTR. PRC-369 (FÊNIX) | J15: 2.27 | K15: A02 | L15: DER SR4 | O15: 24 | P15: PAV | Q15: SC | R15: CAUQ | S15: 7 | T15: 2.4 | U15: 0 | V15: 980 | W15: 0 | X15: 0 | Y15: 0 | Z15: 2.27 | AA15: 0 | AB15: =SUM(W15:AA15)-J15 -> 0 | AE15: 0 | AF15: 0 | AG15: 0 | AH15: 2.27 | AI15: 0 | AJ15: =SUM(AE15:AI15)-J15 -> 0 | AN15: =ROUNDUP(V15*J15,0) -> 2225 | AQ15: Noroeste | AR15: =AQ15&" - "&K15 -> Noroeste - A02
A16: 082S0205EPR | B16: 082S0205 | C16: 082 | D16: 0205 | E16: 082S | F16: S | G16: 082|0205 | H16: ENTR. PRC-369 (FÊNIX) | I16: ACESSO A FÊNIX | J16: 0.48 | K16: A02 | L16: DER SR4 | O16: 24 | P16: PAV | Q16: SC | R16: CAUQ | S16: 7 | T16: 2.4 | U16: 0 | V16: 980 | W16: 0 | X16: 0 | Y16: 0 | Z16: 0.48 | AA16: 0 | AB16: =SUM(W16:AA16)-J16 -> 0 | AE16: 0 | AF16: 0 | AG16: 0 | AH16: 0.48 | AI16: 0 | AJ16: =SUM(AE16:AI16)-J16 -> 0 | AN16: =ROUNDUP(V16*J16,0) -> 471 | AQ16: Noroeste | AR16: =AQ16&" - "&K16 -> Noroeste - A02
A17: 082S0210EPR | B17: 082S0210 | C17: 082 | D17: 0210 | E17: 082S | F17: S | G17: 082|0210 | H17: ACESSO A FÊNIX | I17: AC. SECUND. QUINTA DO SOL | J17: 18.35 | K17: A02 | L17: DER SR4 | O17: 24 | P17: PAV | Q17: SC | R17: CAUQ | S17: 7 | T17: 2.4 | U17: 0 | V17: 974 | W17: 0 | X17: 0 | Y17: 0 | Z17: 18.35 | AA17: 0 | AB17: =SUM(W17:AA17)-J17 -> 0 | AE17: 0 | AF17: 0 | AG17: 0 | AH17: 18.35 | AI17: 0 | AJ17: =SUM(AE17:AI17)-J17 -> 0 | AN17: =ROUNDUP(V17*J17,0) -> 17873 | AQ17: Noroeste | AR17: =AQ17&" - "&K17 -> Noroeste - A02
... A50: 082S0460EPR | B50: 082S0460 | C50: 082 | D50: 0460 | E50: 082S | F50: S | G50: 082|0460 | H50: ENTR. PR-485 (ICARAÍMA) (B) | I50: (ICARAÍMA) (C) | J50: 1.72 | K50: A10 | L50: DER SR4 | O50: 32 | P50: PAV | Q50: Solo-solo | R50: CAUQ | S50: 7 | T50: 0.5 | U50: 0 | V50: 420 | W50: 0 | X50: 0 | Y50: 0 | Z50: 1.72 | AA50: 0 | AB50: =SUM(W50:AA50)-J50 -> 0 | AE50: 0 | AF50: 0 | AG50: 0 | AH50: 1.72 | AI50: 0 | AJ50: =SUM(AE50:AI50)-J50 -> 0 | AN50: =ROUNDUP(V50*J50,0) -> 723 | AQ50: Noroeste | AR50: =AQ50&" - "&K50 -> Noroeste - A10
A51: 082S0470EPR | B51: 082S0470 | C51: 082 | D51: 0470 | E51: 082S | F51: S | G51: 082|0470 | H51: (ICARAÍMA) (C) | I51: ENTR. BR-487 (AC. PONTE S/ RIO PARANÁ) | J51: 11.65 | K51: A10 | L51: DER SR4 | P51: PAV | Q51: Solo-solo | R51: CAUQ | S51: 7 | T51: 0.5 | U51: 0 | V51: 420 | W51: 0 | X51: 0 | Y51: 0 | Z51: 11.65 | AA51: 0 | AB51: =SUM(W51:AA51)-J51 -> 0 | AE51: 0 | AF51: 0 | AG51: 0 | AH51: 11.65 | AI51: 0 | AJ51: =SUM(AE51:AI51)-J51 -> 0 | AN51: =ROUNDUP(V51*J51,0) -> 4893 | AQ51: Noroeste | AR51: =AQ51&" - "&K51 -> Noroeste - A10
A52: 090D0010EPR | B52: 090D0010 | C52: 090 | D52: 0010 | E52: 090D | F52: D | G52: 090|0010D | H52: ENTR. PR-418 (CURITIBA) | I52: FINAL PISTA DUPLA | J52: 1.3 | K52: A03 | L52: DER SR1 | O52: 3 | P52: DUP | Q52: BG | R52: CAUQ | S52: 8.2678159 | T52: 0 | U52: 0 | V52: 6995 | W52: 0 | X52: 0 | Y52: 1.3 | Z52: 0 | AA52: 0 | AB52: =SUM(W52:AA52)-J52 -> 0 | AE52: 0 | AF52: 0 | AG52: 1.3 | AH52: 0 | AI52: 0 | AJ52: =SUM(AE52:AI52)-J52 -> 0 | AN52: =ROUNDUP(V52*J52,0) -> 9094 | AQ52: Leste | AR52: =AQ52&" - "&K52 -> Leste - A03
A53: 090E0010EPR | B53: 090E0010 | C53: 090 | D53: 0010 | E53: 090E | F53: E | G53: 090|0010E | H53: ENTR. PR-418 (CURITIBA) | I53: FINAL PISTA DUPLA | J53: 1.3 | K53: A03 | L53: DER SR1 | O53: 3 | P53: DUP | Q53: BG | R53: CAUQ | S53: 8.2678159 | T53: 0 | U53: 0 | V53: 6995 | W53: 0 | X53: 0 | Y53: 1.3 | Z53: 0 | AA53: 0 | AB53: =SUM(W53:AA53)-J53 -> 0 | AE53: 0 | AF53: 0 | AG53: 1.3 | AH53: 0 | AI53: 0 | AJ53: =SUM(AE53:AI53)-J53 -> 0 | AN53: =ROUNDUP(V53*J53,0) -> 9094 | AQ53: Leste | AR53: =AQ53&" - "&K53 -> Leste - A03
A54: 090S0011EPR | B54: 090S0011 | C54: 090 | D54: 0011 | E54: 090S | F54: S | G54: 090|0011 | H54: FINAL PISTA DUPLA | I54: CAMPO MAGRO | J54: 6.7 | K54: A03 | L54: DER SR1 | O54: 3 | P54: PAV | Q54: SE | R54: CAUQ | S54: 8.487403 | T54: 2.5 | U54: 0 | V54: 8953 | W54: 0 | X54: 0 | Y54: 3.7 | Z54: 3 | AA54: 0 | AB54: =SUM(W54:AA54)-J54 -> 0 | AE54: 0 | AF54: 0 | AG54: 3.7 | AH54: 3 | AI54: 0 | AJ54: =SUM(AE54:AI54)-J54 -> 0 | AN54: =ROUNDUP(V54*J54,0) -> 59986 | AQ54: Leste | AR54: =AQ54&" - "&K54 -> Leste - A03
A55: 090S0012EPR | B55: 090S0012 | C55: 090 | D55: 0012 | E55: 090S | F55: S | G55: 090|0012 | H55: CAMPO MAGRO | I55: ENTR. PR-510 (A) (BATEIAS) | J55: 9.54 | K55: A03 | L55: DER SR1 | O55: 3 | P55: PAV | Q55: SE | R55: CAUQ | S55: 8.0376939 | T55: 2.5 | U55: 0 | V55: 1461 | W55: 0 | X55: 0 | Y55: 2 | Z55: 7.54 | AA55: 0 | AB55: =SUM(W55:AA55)-J55 -> 0 | AE55: 0 | AF55: 0 | AG55: 2 | AH55: 7.54 | AI55: 0 | AJ55: =SUM(AE55:AI55)-J55 -> 0 | AN55: =ROUNDUP(V55*J55,0) -> 13938 | AQ55: Leste | AR55: =AQ55&" - "&K55 -> Leste - A03
A56: 090S0014EPR | B56: 090S0014 | C56: 090 | D56: 0014 | E56: 090S | F56: S | G56: 090|0014 | H56: ENTR. PR-510 (A) (BATEIAS) | I56: ENTR. PR-510 (B) / 509(PLAN.) (BATEIAS) | J56: 0.93 | K56: A03 | L56: DER SR1 | O56: 3 | P56: PAV | Q56: BG | R56: CAUQ | S56: 8.5741935 | T56: 2.5 | U56: 0 | V56: 632 | W56: 0 | X56: 0 | Y56: 0 | Z56: 0.93 | AA56: 0 | AB56: =SUM(W56:AA56)-J56 -> 0 | AE56: 0 | AF56: 0 | AG56: 0 | AH56: 0.93 | AI56: 0 | AJ56: =SUM(AE56:AI56)-J56 -> 0 | AN56: =ROUNDUP(V56*J56,0) -> 588 | AQ56: Leste | AR56: =AQ56&" - "&K56 -> Leste - A03
A57: 090S0030EPR | B57: 090S0030 | C57: 090 | D57: 0030 | E57: 090S | F57: S | G57: 090|0030 | H57: ENTR. PR-510 (B)/509(PLAN.) (BATEIAS) | I57: FINAL DO PAVIMENTO (2ª PONTE RIO DO CERNE) | J57: 8.38 | K57: A03 | L57: DER SR1 | O57: 3 | P57: PAV | Q57: BG | R57: CAUQ | S57: 9.3234224 | T57: 1.5 | U57: 1.1 | V57: 1171 | W57: 0 | X57: 0 | Y57: 0 | Z57: 8.38 | AA57: 0 | AB57: =SUM(W57:AA57)-J57 -> 0 | AE57: 0 | AF57: 0 | AG57: 0 | AH57: 8.38 | AI57: 0 | AJ57: =SUM(AE57:AI57)-J57 -> 0 | AN57: =ROUNDUP(V57*J57,0) -> 9813 | AQ57: Leste | AR57: =AQ57&" - "&K57 -> Leste - A03
A58: 090S0075EPR | B58: 090S0075 | C58: 090 | D58: 0075 | E58: 090S | F58: S | G58: 090|0075 | H58: INÍCIO DO PAVIMENTO (ABAPÃ) | I58: ENTR. PR-340 (P/ CASTROLANDA) | J58: 18.83 | K58: A02 | L58: DER SR2 | O58: 7 | P58: PAV | Q58: BG | R58: CAUQ | S58: 7 | T58: 1.5 | U58: 0 | V58: 1812 | W58: 0 | X58: 0 | Y58: 9 | Z58: 9.83 | AA58: 0 | AB58: =SUM(W58:AA58)-J58 -> 0 | AE58: 0 | AF58: 0 | AG58: 9 | AH58: 9.83 | AI58: 0 | AJ58: =SUM(AE58:AI58)-J58 -> 0 | AN58: =ROUNDUP(V58*J58,0) -> 34120 | AQ58: Campos Gerais | AR58: =AQ58&" - "&K58 -> Campos Gerais - A02
A59: 090S0080EPR | B59: 090S0080 | C59: 090 | D59: 0080 | E59: 090S | F59: S | G59: 090|0080 | H59: ENTR. PR-340 (P/ CASTROLANDA) | I59: ENTR. PR-429 Contorno de Castro | J59: 3.07 | K59: A01 | L59: DER SR2 | O59: 6 | P59: PAV | Q59: BG | R59: CAUQ | S59: 7 | T59: 1.5 | U59: 0 | V59: 1812 | W59: 0 | X59: 0 | Y59: 0.07 | Z59: 3 | AA59: 0 | AB59: =SUM(W59:AA59)-J59 -> 0 | AE59: 0 | AF59: 0 | AG59: 0.07 | AH59: 3 | AI59: 0 | AJ59: =SUM(AE59:AI59)-J59 -> 0 | AN59: =ROUNDUP(V59*J59,0) -> 5563 | AQ59: Campos Gerais | AR59: =AQ59&" - "&K59 -> Campos Gerais - A01
A60: 090S0150EPR | B60: 090S0150 | C60: 090 | D60: 0150 | E60: 090S | F60: S | G60: 090|0150 | H60: ENTR. PR-151 (B) (PIRAÍ DO SUL) | I60: ACESSO I PIRAÍ DO SUL. | J60: 0.85 | K60: A01 | L60: DER SR2 | O60: 6 | P60: PAV | Q60: SC | R60: CAUQ | S60: 7.3 | T60: 0 | U60: 0 | V60: 2819 | W60: 0 | X60: 0 | Y60: 0 | Z60: 0.85 | AA60: 0 | AB60: =SUM(W60:AA60)-J60 -> 0 | AE60: 0 | AF60: 0 | AG60: 0 | AH60: 0.85 | AI60: 0 | AJ60: =SUM(AE60:AI60)-J60 -> 0 | AN60: =ROUNDUP(V60*J60,0) -> 2397 | AQ60: Campos Gerais | AR60: =AQ60&" - "&K60 -> Campos Gerais - A01
A61: 090S0153EPR | B61: 090S0153 | C61: 090 | D61: 0153 | E61: 090S | F61: S | G61: 090|0153 | H61: ACESSO I PIRAÍ DO SUL | I61: ACESSO II PIRAÍ DO SUL | J61: 1.97 | K61: A01 | L61: DER SR2 | O61: 6 | P61: PAV | Q61: SC | R61: CAUQ | S61: 7.2 | T61: 0 | U61: 0 | V61: 2819 | W61: 0 | X61: 0 | Y61: 0 | Z61: 1.97 | AA61: 0 | AB61: =SUM(W61:AA61)-J61 -> 0 | AE61: 0 | AF61: 0 | AG61: 0 | AH61: 1.97 | AI61: 0 | AJ61: =SUM(AE61:AI61)-J61 -> 0 | AN61: =ROUNDUP(V61*J61,0) -> 5554 | AQ61: Campos Gerais | AR61: =AQ61&" - "&K61 -> Campos Gerais - A01
A62: 090S0156EPR | B62: 090S0156 | C62: 090 | D62: 0156 | E62: 090S | F62: S | G62: 090|0156 | H62: ACESSO II PIRAÍ DO SUL | I62: FIM TRECHO OFERTADO | J62: 22.2 | K62: A01 | L62: DER SR2 | O62: 6 | P62: PAV | Q62: SC | R62: CAUQ | S62: 7.3 | T62: 0 | U62: 0 | V62: 2404 | W62: 0 | X62: 0 | Y62: 6 | Z62: 16.2 | AA62: 0 | AB62: =SUM(W62:AA62)-J62 -> 0 | AE62: 0 | AF62: 0 | AG62: 6 | AH62: 16.2 | AI62: 0 | AJ62: =SUM(AE62:AI62)-J62 -> 0 | AN62: =ROUNDUP(V62*J62,0) -> 53369 | AQ62: Campos Gerais | AR62: =AQ62&" - "&K62 -> Campos Gerais - A01
A63: 090S0160EPR | B63: 090S0160 | C63: 090 | D63: 0160 | E63: 090S | F63: S | G63: 090|0160 | H63: FIM TRECHO OFERTADO | I63: ENTR. PR-239 (A) (P/ ARAPOTI) | J63: 15.74 | K63: A01 | L63: DER SR2 | O63: 6 | P63: PAV | Q63: BG | R63: CAUQ | S63: 7 | T63: 1.5 | U63: 1 | V63: 2819 | W63: 0 | X63: 0 | Y63: 4 | Z63: 11.74 | AA63: 0 | AB63: =SUM(W63:AA63)-J63 -> 0 | AE63: 0 | AF63: 0 | AG63: 4 | AH63: 11.74 | AI63: 0 | AJ63: =SUM(AE63:AI63)-J63 -> 0 | AN63: =ROUNDUP(V63*J63,0) -> 44372 | AQ63: Campos Gerais | AR63: =AQ63&" - "&K63 -> Campos Gerais - A01
... A66: 090S0200EPR | B66: 090S0200 | C66: 090 | D66: 0200 | E66: 090S | F66: S | G66: 090|0200 | H66: ENTR. PR-239(B)(PLAN.) (VENTANIA) | I66: ENTR. PRC-153 (P/ IBAITI)/BR-153 (P/ TIBAGI) | J66: 4.87 | K66: A01 | L66: DER SR2 | O66: 6 | P66: PAV | Q66: BG | R66: CAUQ | S66: 7 | T66: 1.5 | U66: 0 | V66: 849 | W66: 0 | X66: 0 | Y66: 1 | Z66: 3.87 | AA66: 0 | AB66: =SUM(W66:AA66)-J66 -> 0 | AE66: 0 | AF66: 0 | AG66: 1 | AH66: 3.87 | AI66: 0 | AJ66: =SUM(AE66:AI66)-J66 -> 0 | AN66: =ROUNDUP(V66*J66,0) -> 4135 | AQ66: Campos Gerais | AR66: =AQ66&" - "&K66 -> Campos Gerais - A01
A67: 090S0210EPR | B67: 090S0210 | C67: 090 | D67: 0210 | E67: 090S | F67: S | G67: 090|0210 | H67: ENTR. PRC-153 (P/ IBAITI) / ENTR. BR-153 (P/ TIBAGI) | I67: ACESSO À BARRO PRETO | J67: 12.25 | K67: A08 | L67: DER SR3 | O67: 20 | P67: PAV | Q67: BG | R67: CAUQ | S67: 7 | T67: 1.5 | U67: 0 | V67: 1744 | W67: 0 | X67: 0 | Y67: 1 | Z67: 11.25 | AA67: 0 | AB67: =SUM(W67:AA67)-J67 -> 0 | AE67: 0 | AF67: 0 | AG67: 1 | AH67: 11.25 | AI67: 0 | AJ67: =SUM(AE67:AI67)-J67 -> 0 | AN67: =ROUNDUP(V67*J67,0) -> 21364 | AQ67: Norte | AR67: =AQ67&" - "&K67 -> Norte - A08
A68: 090S0215EPR | B68: 090S0215 | C68: 090 | D68: 0215 | E68: 090S | F68: S | G68: 090|0215 | H68: ACESSO À BARRO PRETO | I68: ALECRIM | J68: 18.81 | K68: A08 | L68: DER SR3 | O68: 20 | P68: PAV | Q68: BG | R68: CAUQ | S68: 7 | T68: 1.5 | U68: 0 | V68: 1351 | W68: 0 | X68: 0 | Y68: 2 | Z68: 16.81 | AA68: 0 | AB68: =SUM(W68:AA68)-J68 -> 0 | AE68: 0 | AF68: 0 | AG68: 2 | AH68: 16.81 | AI68: 0 | AJ68: =SUM(AE68:AI68)-J68 -> 0 | AN68: =ROUNDUP(V68*J68,0) -> 25413 | AQ68: Norte | AR68: =AQ68&" - "&K68 -> Norte - A08
A69: 090S0220EPR | B69: 090S0220 | C69: 090 | D69: 0220 | E69: 090S | F69: S | G69: 090|0220 | H69: ALECRIM | I69: ENTR. PR-160 (A) (CURIÚVA) | J69: 6.09 | K69: A08 | L69: DER SR3 | O69: 20 | P69: PAV | Q69: BG | R69: CAUQ | S69: 7 | T69: 1.5 | U69: 0 | V69: 1873 | W69: 0 | X69: 0 | Y69: 0 | Z69: 6.09 | AA69: 0 | AB69: =SUM(W69:AA69)-J69 -> 0 | AE69: 0 | AF69: 0 | AG69: 0 | AH69: 6.09 | AI69: 0 | AJ69: =SUM(AE69:AI69)-J69 -> 0 | AN69: =ROUNDUP(V69*J69,0) -> 11407 | AQ69: Norte | AR69: =AQ69&" - "&K69 -> Norte - A08
A70: 090S0230EPR | B70: 090S0230 | C70: 090 | D70: 0230 | E70: 090S | F70: S | G70: 090|0230 | H70: ENTR. PR-160(A) (CURIÚVA) | I70: ENTR. PR-160(B) (CURIÚVA) | J70: 2.73 | K70: A08 | L70: DER SR3 | O70: 20 | P70: PAV | Q70: BG | R70: CAUQ | S70: 7 | T70: 1.5 | U70: 1.7 | V70: 3722 | W70: 0 | X70: 0 | Y70: 1 | Z70: 1.73 | AA70: 0 | AB70: =SUM(W70:AA70)-J70 -> 0 | AE70: 0 | AF70: 0 | AG70: 1 | AH70: 1.73 | AI70: 0 | AJ70: =SUM(AE70:AI70)-J70 -> 0 | AN70: =ROUNDUP(V70*J70,0) -> 10162 | AQ70: Norte | AR70: =AQ70&" - "&K70 -> Norte - A08
A71: 090S0250EPR | B71: 090S0250 | C71: 090 | D71: 0250 | E71: 090S | F71: S | G71: 090|0250 | H71: ENTR. PR-160(B) (CURIÚVA) | I71: ENTR. BR-272(PLAN.) AC. A SAPOPEMA | J71: 18.86 | K71: A08 | L71: DER SR3 | O71: 20 | P71: PAV | Q71: BG | R71: CAUQ | S71: 6.6 | T71: 1.5 | U71: 2.9 | V71: 2276 | W71: 0 | X71: 0 | Y71: 0 | Z71: 18.86 | AA71: 0 | AB71: =SUM(W71:AA71)-J71 -> 0 | AE71: 0 | AF71: 0 | AG71: 0 | AH71: 18.86 | AI71: 0 | AJ71: =SUM(AE71:AI71)-J71 -> 0 | AN71: =ROUNDUP(V71*J71,0) -> 42926 | AQ71: Norte | AR71: =AQ71&" - "&K71 -> Norte - A08
A72: 090S0270EPR | B72: 090S0270 | C72: 090 | D72: 0270 | E72: 090S | F72: S | G72: 090|0270 | H72: ENTR. BR-272(PLAN.) AC. A SAPOPEMA | I72: AC. SÃO JERÔNIMO DA SERRA | J72: 32.57 | K72: A04 | L72: DER SR3 | O72: 16 | P72: PAV | Q72: BG | R72: CAUQ | S72: 6.6 | T72: 1.5 | U72: 5.9 | V72: 1156 | W72: 0 | X72: 0 | Y72: 6 | Z72: 26.57 | AA72: 0 | AB72: =SUM(W72:AA72)-J72 -> 0 | AE72: 0 | AF72: 0 | AG72: 6 | AH72: 26.57 | AI72: 0 | AJ72: =SUM(AE72:AI72)-J72 -> 0 | AN72: =ROUNDUP(V72*J72,0) -> 37651 | AQ72: Norte | AR72: =AQ72&" - "&K72 -> Norte - A04
A73: 090S0290EPR | B73: 090S0290 | C73: 090 | D73: 0290 | E73: 090S | F73: S | G73: 090|0290 | H73: AC. SÃO JERÔNIMO DA SERRA | I73: ENTR. ROD. MUN. P/ CONGONHINHAS (NÃO PAV.) | J73: 0.95 | K73: A04 | L73: DER SR3 | O73: 16 | P73: PAV | Q73: BG | R73: CAUQ | S73: 7.2 | T73: 2.5 | U73: 0 | V73: 1049 | W73: 0 | X73: 0 | Y73: 0 | Z73: 0.95 | AA73: 0 | AB73: =SUM(W73:AA73)-J73 -> 0 | AE73: 0 | AF73: 0 | AG73: 0 | AH73: 0.95 | AI73: 0 | AJ73: =SUM(AE73:AI73)-J73 -> 0 | AN73: =ROUNDUP(V73*J73,0) -> 997 | AQ73: Norte | AR73: =AQ73&" - "&K73 -> Norte - A04
A74: 090S0295EPR | B74: 090S0295 | C74: 090 | D74: 0295 | E74: 090S | F74: S | G74: 090|0295 | H74: ENTR. ROD. MUN. P/ CONGONHINHAS (NÃO PAV.) | I74: AC. NOVA STA. BÁRBARA | J74: 14.09 | K74: A04 | L74: DER SR3 | O74: 16 | P74: PAV | Q74: BG | R74: CAUQ | S74: 7.2 | T74: 2.5 | U74: 0 | V74: 1049 | W74: 0 | X74: 0 | Y74: 0 | Z74: 14.09 | AA74: 0 | AB74: =SUM(W74:AA74)-J74 -> 0 | AE74: 0 | AF74: 0 | AG74: 0 | AH74: 14.09 | AI74: 0 | AJ74: =SUM(AE74:AI74)-J74 -> 0 | AN74: =ROUNDUP(V74*J74,0) -> 14781 | AQ74: Norte | AR74: =AQ74&" - "&K74 -> Norte - A04
A75: 090S0300EPR | B75: 090S0300 | C75: 090 | D75: 0300 | E75: 090S | F75: S | G75: 090|0300 | H75: AC. NOVA STA. BÁRBARA | I75: AC. SANTA CECÍLIA DO PAVÃO | J75: 8.61 | K75: A04 | L75: DER SR3 | O75: 16 | P75: PAV | Q75: BG | R75: CAUQ | S75: 7.2 | T75: 2.5 | U75: 0 | V75: 1049 | W75: 0 | X75: 0 | Y75: 0 | Z75: 8.61 | AA75: 0 | AB75: =SUM(W75:AA75)-J75 -> 0 | AE75: 0 | AF75: 0 | AG75: 0 | AH75: 8.61 | AI75: 0 | AJ75: =SUM(AE75:AI75)-J75 -> 0 | AN75: =ROUNDUP(V75*J75,0) -> 9032 | AQ75: Norte | AR75: =AQ75&" - "&K75 -> Norte - A04
A76: 090S0310EPR | B76: 090S0310 | C76: 090 | D76: 0310 | E76: 090S | F76: S | G76: 090|0310 | H76: AC. SANTA CECÍLIA DO PAVÃO | I76: AC. SECUND. STA. CECÍLIA DO PAVÃO | J76: 0.85 | K76: A04 | L76: DER SR3 | O76: 16 | P76: PAV | Q76: BG | R76: CAUQ | S76: 7.2 | T76: 2.5 | U76: 0 | V76: 4243 | W76: 0 | X76: 0 | Y76: 0.85 | Z76: 0 | AA76: 0 | AB76: =SUM(W76:AA76)-J76 -> 0 | AE76: 0 | AF76: 0 | AG76: 0.85 | AH76: 0 | AI76: 0 | AJ76: =SUM(AE76:AI76)-J76 -> 0 | AN76: =ROUNDUP(V76*J76,0) -> 3607 | AQ76: Norte | AR76: =AQ76&" - "&K76 -> Norte - A04
A77: 090S0320EPR | B77: 090S0320 | C77: 090 | D77: 0320 | E77: 090S | F77: S | G77: 090|0320 | H77: AC. SECUND. STA. CECÍLIA DO PAVÃO | I77: ENTR. PR-218 (P/ S. SEB. DA AMOREIRA) | J77: 7.8 | K77: A04 | L77: DER SR3 | O77: 16 | P77: PAV | Q77: BG | R77: CAUQ | S77: 7.2 | T77: 2.5 | U77: 0 | V77: 4243 | W77: 0 | X77: 0 | Y77: 0 | Z77: 7.8 | AA77: 0 | AB77: =SUM(W77:AA77)-J77 -> 0 | AE77: 0 | AF77: 0 | AG77: 0 | AH77: 7.8 | AI77: 0 | AJ77: =SUM(AE77:AI77)-J77 -> 0 | AN77: =ROUNDUP(V77*J77,0) -> 33096 | AQ77: Norte | AR77: =AQ77&" - "&K77 -> Norte - A04
A78: 090S0330EPR | B78: 090S0330 | C78: 090 | D78: 0330 | E78: 090S | F78: S | G78: 090|0330 | H78: ENTR. PR-218 (P/ S. SEB. DA AMOREIRA) | I78: ACESSO CEBOLÃO | J78: 8.82 | K78: A04 | L78: DER SR3 | O78: 16 | P78: PAV | Q78: BG | R78: CAUQ | S78: 7 | T78: 2.5 | U78: 0 | V78: 4243 | W78: 0 | X78: 0 | Y78: 0 | Z78: 8.82 | AA78: 0 | AB78: =SUM(W78:AA78)-J78 -> 0 | AE78: 0 | AF78: 0 | AG78: 0 | AH78: 8.82 | AI78: 0 | AJ78: =SUM(AE78:AI78)-J78 -> 0 | AN78: =ROUNDUP(V78*J78,0) -> 37424 | AQ78: Norte | AR78: =AQ78&" - "&K78 -> Norte - A04
A79: 090S0335EPR | B79: 090S0335 | C79: 090 | D79: 0335 | E79: 090S | F79: S | G79: 090|0335 | H79: ACESSO CEBOLÃO | I79: AC. I ASSAÍ | J79: 1.95 | K79: A04 | L79: DER SR3 | O79: 16 | P79: PAV | Q79: BG | R79: CAUQ | S79: 7 | T79: 2.5 | U79: 0 | V79: 4442 | W79: 0 | X79: 0 | Y79: 0 | Z79: 1.95 | AA79: 0 | AB79: =SUM(W79:AA79)-J79 -> 0 | AE79: 0 | AF79: 0 | AG79: 0 | AH79: 1.95 | AI79: 0 | AJ79: =SUM(AE79:AI79)-J79 -> 0 | AN79: =ROUNDUP(V79*J79,0) -> 8662 | AQ79: Norte | AR79: =AQ79&" - "&K79 -> Norte - A04
... A91: 092S0010EPR | B91: 092S0010 | C91: 092 | D91: 0010 | E91: 092S | F91: S | G91: 092|0010 | H91: PONTE RIO BARIGUI (CURITIBA) | I91: ENTR. PR-418 (CONT. NORTE CURITIBA) | J91: 0.33 | K91: A02 | L91: DER SR1 | O91: 2 | P91: PAV | Q91: SC | R91: CAUQ | S91: 6.94 | T91: 2.5 | U91: 0 | V91: 21916 | W91: 0 | X91: 0 | Y91: 0 | Z91: 0.33 | AA91: 0 | AB91: =SUM(W91:AA91)-J91 -> 0 | AE91: 0 | AF91: 0 | AG91: 0 | AH91: 0.33 | AI91: 0 | AJ91: =SUM(AE91:AI91)-J91 -> 0 | AN91: =ROUNDUP(V91*J91,0) -> 7233 | AQ91: Leste | AR91: =AQ91&" - "&K91 -> Leste - A02
A92: 092O0015EPR | B92: 092O0015 | C92: 092 | D92: 0015 | E92: 092O | F92: O | G92: 092|0015 | H92: ENTR. PR-418 (CONT. NORTE CURITIBA) | I92: AC. PRINCIPAL ALM. TAMANDARÉ | J92: 4.82 | K92: A02 | L92: DER SR1 | P92: EOD | Q92: SC | R92: CAUQ | S92: 6.94 | T92: 2.5 | U92: 0 | V92: 21916 | W92: 0 | X92: 0 | Y92: 0.82 | Z92: 4 | AA92: 0 | AB92: =SUM(W92:AA92)-J92 -> 0 | AE92: 0 | AF92: 0 | AG92: 0.82 | AH92: 4 | AI92: 0 | AJ92: =SUM(AE92:AI92)-J92 -> 0 | AN92: =ROUNDUP(V92*J92,0) -> 105636 | AQ92: Leste | AR92: =AQ92&" - "&K92 -> Leste - A02
A93: 092S0020EPR | B93: 092S0020 | C93: 092 | D93: 0020 | E93: 092S | F93: S | G93: 092|0020 | H93: AC. PRINCIPAL ALM. TAMANDARÉ | I93: ENTR. PR-509 (ALMIRANTE TAMANDARÉ) | J93: 0.22 | K93: A02 | L93: DER SR1 | O93: 2 | P93: PAV | Q93: SC | R93: CAUQ | S93: 7.0681818 | T93: 2.5 | U93: 0 | V93: 15879 | W93: 0 | X93: 0 | Y93: 0 | Z93: 0.22 | AA93: 0 | AB93: =SUM(W93:AA93)-J93 -> 0 | AE93: 0 | AF93: 0 | AG93: 0 | AH93: 0.22 | AI93: 0 | AJ93: =SUM(AE93:AI93)-J93 -> 0 | AN93: =ROUNDUP(V93*J93,0) -> 3494 | AQ93: Leste | AR93: =AQ93&" - "&K93 -> Leste - A02
A94: 092S0030EPR | B94: 092S0030 | C94: 092 | D94: 0030 | E94: 092S | F94: S | G94: 092|0030 | H94: ENTR. PR-509 (ALMIRANTE TAMANDARÉ) | I94: ACESSO TRANQUEIRA | J94: 6.28 | K94: A02 | L94: DER SR1 | O94: 2 | P94: PAV | Q94: SC | R94: CAUQ | S94: 8.6670271 | T94: 1.5 | U94: 2.4 | V94: 15879 | W94: 0 | X94: 1 | Y94: 4 | Z94: 1.28 | AA94: 0 | AB94: =SUM(W94:AA94)-J94 -> 0 | AE94: 0 | AF94: 1 | AG94: 4 | AH94: 1.28 | AI94: 0 | AJ94: =SUM(AE94:AI94)-J94 -> 0 | AN94: =ROUNDUP(V94*J94,0) -> 99721 | AQ94: Leste | AR94: =AQ94&" - "&K94 -> Leste - A02
A95: 092S0035EPR | B95: 092S0035 | C95: 092 | D95: 0035 | E95: 092S | F95: S | G95: 092|0035 | H95: ACESSO TRANQUEIRA | I95: ENTR. PR-800 (AC. ITAPERUÇU) | J95: 4.87 | K95: A02 | L95: DER SR1 | O95: 2 | P95: PAV | Q95: SC | R95: CAUQ | S95: 7.7349076 | T95: 2 | U95: 0.9 | V95: 15015 | W95: 0 | X95: 1 | Y95: 3.87 | Z95: 0 | AA95: 0 | AB95: =SUM(W95:AA95)-J95 -> 0 | AE95: 0 | AF95: 1 | AG95: 3.87 | AH95: 0 | AI95: 0 | AJ95: =SUM(AE95:AI95)-J95 -> 0 | AN95: =ROUNDUP(V95*J95,0) -> 73124 | AQ95: Leste | AR95: =AQ95&" - "&K95 -> Leste - A02
A96: 092S0040EPR | B96: 092S0040 | C96: 092 | D96: 0040 | E96: 092S | F96: S | G96: 092|0040 | H96: ENTR. PR-800 (AC. ITAPERUÇU) | I96: RIO BRANCO DO SUL (A) (VIADUTO LINHA FÉRREA) | J96: 3.14 | K96: A02 | L96: DER SR1 | O96: 2 | P96: PAV | Q96: SC | R96: CAUQ | S96: 9.4165605 | T96: 2.5 | U96: 2.2 | V96: 12264 | W96: 0 | X96: 0 | Y96: 1 | Z96: 2.14 | AA96: 0 | AB96: =SUM(W96:AA96)-J96 -> 0 | AE96: 0 | AF96: 0 | AG96: 1 | AH96: 2.14 | AI96: 0 | AJ96: =SUM(AE96:AI96)-J96 -> 0 | AN96: =ROUNDUP(V96*J96,0) -> 38509 | AQ96: Leste | AR96: =AQ96&" - "&K96 -> Leste - A02
A97: 092S0050EPR | B97: 092S0050 | C97: 092 | D97: 0050 | E97: 092S | F97: S | G97: 092|0050 | H97: RIO BRANCO SUL (B) (FÁB. VOTORAN) | I97: R. BRANCO DO SUL (R. 7 DE ABRIL) | J97: 2.66 | K97: A02 | L97: DER SR1 | O97: 2 | P97: PAV | Q97: SC | R97: CAUQ | S97: 7.3229323 | T97: 0 | U97: 0 | V97: 3354 | W97: 0 | X97: 0 | Y97: 2 | Z97: 0.66 | AA97: 0 | AB97: =SUM(W97:AA97)-J97 -> 0 | AE97: 0 | AF97: 0 | AG97: 2 | AH97: 0.66 | AI97: 0 | AJ97: =SUM(AE97:AI97)-J97 -> 0 | AN97: =ROUNDUP(V97*J97,0) -> 8922 | AQ97: Leste | AR97: =AQ97&" - "&K97 -> Leste - A02
A98: 092S0060EPR | B98: 092S0060 | C98: 092 | D98: 0060 | E98: 092S | F98: S | G98: 092|0060 | H98: R. BRANCO DO SUL (R. 7 DE ABRIL) | I98: CERRO AZUL (A) | J98: 49.39 | K98: A02 | L98: DER SR1 | O98: 2 | P98: PAV | Q98: SC | R98: CAUQ | S98: 8.2074798 | T98: 1.5 | U98: 5.6 | V98: 1249 | W98: 0 | X98: 7 | Y98: 12.39 | Z98: 25 | AA98: 5 | AB98: =SUM(W98:AA98)-J98 -> 0 | AE98: 0 | AF98: 7 | AG98: 12.39 | AH98: 25 | AI98: 5 | AJ98: =SUM(AE98:AI98)-J98 -> 0 | AN98: =ROUNDUP(V98*J98,0) -> 61689 | AQ98: Leste | AR98: =AQ98&" - "&K98 -> Leste - A02
A99: 092M0065MUN | B99: 092M0065 | C99: 092 | D99: 0065 | E99: 092M | F99: M | G99: 092|0065 | H99: CERRO AZUL (A) | I99: CERRO AZUL (B) | J99: 1.31 | K99: A02 | L99: DER SR1 | O99: 2 | P99: MUN | Q99: SB | R99: CAUQ | S99: 9 | T99: 0 | U99: 0 | V99: 1686 | W99: 0 | X99: 0 | Y99: 1.74 | Z99: 0 | AA99: 0 | AB99: =SUM(W99:AA99)-J99 -> 0.43 | AE99: =IF(W99=0,0,W99-$AB99) -> 0 | AF99: =IF(X99=0,0,X99-$AB99) -> 0 | AG99: =IF(Y99=0,0,Y99-$AB99) -> 1.31 | AH99: =IF(Z99=0,0,Z99-$AB99) -> 0 | AI99: =IF(AA99=0,0,AA99-$AB99) -> 0 | AJ99: =SUM(AE99:AI99)-J99 -> 0 | AN99: =ROUNDUP(V99*J99,0) -> 2209 | AQ99: Leste | AR99: =AQ99&" - "&K99 -> Leste - A02
A100: 092S0310EPR | B100: 092S0310 | C100: 092 | D100: 0310 | E100: 092S | F100: S | G100: 092|0310 | H100: ENTR. BR-153(B) (S.A.PLATINA) | I100: ENTR. PR-515 (BARRA DO JACARÉ) | J100: 26.77 | K100: A06 | L100: DER SR3 | N100: =O100 -> 18 | O100: 18 | P100: PAV | Q100: SC | R100: CAUQ | S100: 6.6 | T100: 1.2 | U100: 0 | V100: 1533 | W100: 0 | X100: 9 | Y100: 17.77 | Z100: 0 | AA100: 0 | AB100: =SUM(W100:AA100)-J100 -> 0 | AE100: 0 | AF100: 9 | AG100: 17.77 | AH100: 0 | AI100: 0 | AJ100: =SUM(AE100:AI100)-J100 -> 0 | AN100: =ROUNDUP(V100*J100,0) -> 41039 | AQ100: Norte | AR100: =AQ100&" - "&K100 -> Norte - A06
A101: 092S0330EPR | B101: 092S0330 | C101: 092 | D101: 0330 | E101: 092S | F101: S | G101: 092|0330 | H101: ENTR. PR-515 (BARRA DO JACARÉ) | I101: ACESSO ANDIRÁ | J101: 8.39 | K101: A06 | L101: DER SR3 | N101: =O101 -> 18 | O101: 18 | P101: PAV | Q101: MH | R101: CAUQ | S101: 6.6 | T101: 1.2 | U101: 0 | V101: 3258 | W101: 0 | X101: 4 | Y101: 3.39 | Z101: 1 | AA101: 0 | AB101: =SUM(W101:AA101)-J101 -> 0 | AE101: 0 | AF101: 4 | AG101: 3.39 | AH101: 1 | AI101: 0 | AJ101: =SUM(AE101:AI101)-J101 -> 0 | AN101: =ROUNDUP(V101*J101,0) -> 27335 | AQ101: Norte | AR101: =AQ101&" - "&K101 -> Norte - A06
A102: 092S0340EPR | B102: 092S0340 | C102: 092 | D102: 0340 | E102: 092S | F102: S | G102: 092|0340 | H102: ACESSO ANDIRÁ | I102: ENTR. BR-369 (A) (ANDIRÁ) | J102: 3.49 | K102: A06 | L102: DER SR3 | N102: =O102 -> 18 | O102: 18 | P102: PAV | Q102: MH | R102: CAUQ | S102: 6.6 | T102: 1.2 | U102: 0 | V102: 258 | W102: 0 | X102: 2 | Y102: 0 | Z102: 1.49 | AA102: 0 | AB102: =SUM(W102:AA102)-J102 -> 0 | AE102: 0 | AF102: 2 | AG102: 0 | AH102: 1.49 | AI102: 0 | AJ102: =SUM(AE102:AI102)-J102 -> 0 | AN102: =ROUNDUP(V102*J102,0) -> 901 | AQ102: Norte | AR102: =AQ102&" - "&K102 -> Norte - A06
A103: 092S0350EPR | B103: 092S0350 | C103: 092 | D103: 0350 | E103: 092S | F103: S | G103: 092|0350 | H103: ENTR. BR-369 (B) (ANDIRÁ) | I103: ENTR. PR-517 | J103: 3.91 | K103: A06 | L103: DER SR3 | N103: =O103 -> 18 | O103: 18 | P103: PAV | Q103: SMC | R103: CAUQ | S103: 6.6 | T103: 1.2 | U103: 0 | V103: 734 | W103: 0 | X103: 1 | Y103: 2.91 | Z103: 0 | AA103: 0 | AB103: =SUM(W103:AA103)-J103 -> 0 | AE103: 0 | AF103: 1 | AG103: 2.91 | AH103: 0 | AI103: 0 | AJ103: =SUM(AE103:AI103)-J103 -> 0 | AN103: =ROUNDUP(V103*J103,0) -> 2870 | AQ103: Norte | AR103: =AQ103&" - "&K103 -> Norte - A06
A104: 092S0370EPR | B104: 092S0370 | C104: 092 | D104: 0370 | E104: 092S | F104: S | G104: 092|0370 | H104: ENTR. PR-517 | I104: PORTO LEOPOLDINA | J104: 10.59 | K104: A06 | L104: DER SR3 | N104: =O104 -> 18 | O104: 18 | P104: PAV | Q104: MH | R104: CAUQ | S104: 6 | T104: 0.7 | U104: 0 | V104: 2495 | W104: 0 | X104: 5 | Y104: 5.59 | Z104: 0 | AA104: 0 | AB104: =SUM(W104:AA104)-J104 -> 0 | AE104: 0 | AF104: 5 | AG104: 5.59 | AH104: 0 | AI104: 0 | AJ104: =SUM(AE104:AI104)-J104 -> 0 | AN104: =ROUNDUP(V104*J104,0) -> 26423 | AQ104: Norte | AR104: =AQ104&" - "&K104 -> Norte - A06
A105: 151S0010EPR | B105: 151S0010 | C105: 151 | D105: 0010 | E105: 151S | F105: S | G105: 151|0010 | H105: PORTO EMIGDÃO (DIVISA PR/SP) | I105: ACESSO PONTE NOVA | J105: 0.3 | K105: A06 | L105: DER SR3 | O105: 18 | P105: PAV | Q105: SMC | R105: TSS | S105: 6.6 | T105: 0.3 | U105: 0 | V105: 272 | W105: 0 | X105: 0 | Y105: 0 | Z105: 0.3 | AA105: 0 | AB105: =SUM(W105:AA105)-J105 -> 0 | AE105: 0 | AF105: 0 | AG105: 0 | AH105: 0.3 | AI105: 0 | AJ105: =SUM(AE105:AI105)-J105 -> 0 | AN105: =ROUNDUP(V105*J105,0) -> 82 | AQ105: Norte | AR105: =AQ105&" - "&K105 -> Norte - A06
A106: 151S0020EPR | B106: 151S0020 | C106: 151 | D106: 0020 | E106: 151S | F106: S | G106: 151|0020 | H106: ACESSO PONTE NOVA | I106: ENTR. PR-431 (RIBEIRÃO CLARO) (A) | J106: 12.63 | K106: A06 | L106: DER SR3 | O106: 18 | P106: PAV | Q106: SMC | R106: TSS | S106: 6.6 | T106: 0.3 | U106: 0 | V106: 272 | W106: 0 | X106: 0 | Y106: 2 | Z106: 10.63 | AA106: 0 | AB106: =SUM(W106:AA106)-J106 -> 0 | AE106: 0 | AF106: 0 | AG106: 2 | AH106: 10.63 | AI106: 0 | AJ106: =SUM(AE106:AI106)-J106 -> 0 | AN106: =ROUNDUP(V106*J106,0) -> 3436 | AQ106: Norte | AR106: =AQ106&" - "&K106 -> Norte - A06
A107: 151M0022MUN | B107: 151M0022 | C107: 151 | D107: 0022 | E107: 151M | F107: M | G107: 151|0022 | H107: ENTR. PR-431 (RIBEIRÃO CLARO) (A) | I107: ENTR. RUA GUERINO ZANETI | J107: 0.23 | K107: A06 | L107: DER SR3 | O107: 18 | P107: MUN | Q107: SMC | R107: TSS | S107: 9.5 | T107: 0 | U107: 0 | V107: 211 | W107: 0 | X107: 0 | Y107: 0 | Z107: 0.23 | AA107: 0 | AB107: =SUM(W107:AA107)-J107 -> 0 | AE107: 0 | AF107: 0 | AG107: 0 | AH107: 0.23 | AI107: 0 | AJ107: =SUM(AE107:AI107)-J107 -> 0 | AN107: =ROUNDUP(V107*J107,0) -> 49 | AQ107: Norte | AR107: =AQ107&" - "&K107 -> Norte - A06
A108: 151M0025MUN(A) | B108: 151M0025 | C108: 151 | D108: 0025 | E108: 151M | F108: M | G108: 151|0025 A | H108: ENTR. RUA GUERINO ZANETI | I108: ENTR. RUA WILSON RODRIGUES DE OLIVEIRA | J108: 1.22 | K108: A06 | L108: DER SR3 | O108: 18 | P108: MUN | Q108: SMC | R108: TSS | S108: 9.5 | T108: 0 | U108: 0 | V108: 211 | W108: 0 | X108: 0 | Y108: 0 | Z108: 1.22 | AA108: 0 | AB108: =SUM(W108:AA108)-J108 -> 0 | AE108: 0 | AF108: 0 | AG108: 0 | AH108: 1.22 | AI108: 0 | AJ108: =SUM(AE108:AI108)-J108 -> 0 | AN108: =ROUNDUP(V108*J108,0) -> 258 | AQ108: Norte | AR108: =AQ108&" - "&K108 -> Norte - A06
A109: 151M0025MUN(B) | B109: 151M0025 | C109: 151 | D109: 0025 | E109: 151M | F109: M | G109: 151|0025 B | H109: ENTR. RUA WILSON RODRIGUES DE OLIVEIRA | I109: ENTR. RUA GUERINO ZANETI | J109: 1.42 | K109: A06 | L109: DER SR3 | O109: 18 | P109: MUN | Q109: SMC | R109: TSS | S109: 9.5 | T109: 0 | U109: 0 | V109: 211 | W109: 0 | X109: 0 | Y109: 0 | Z109: 1.42 | AA109: 0 | AB109: =SUM(W109:AA109)-J109 -> 0 | AE109: 0 | AF109: 0 | AG109: 0 | AH109: 1.42 | AI109: 0 | AJ109: =SUM(AE109:AI109)-J109 -> 0 | AN109: =ROUNDUP(V109*J109,0) -> 300 | AQ109: Norte | AR109: =AQ109&" - "&K109 -> Norte - A06
A110: 151M0028MUN | B110: 151M0028 | C110: 151 | D110: 0028 | E110: 151M | F110: M | G110: 151|0028 | H110: ENTR. RUA CEL. EMILIO GOMES | I110: ENTR. RIBEIRÃO CLARO (B) | J110: 0.3 | K110: A06 | L110: DER SR3 | O110: 18 | P110: MUN | Q110: SMC | R110: TSS | S110: 9.5 | T110: 0 | U110: 0 | V110: 211 | W110: 0 | X110: 0 | Y110: 0 | Z110: 0.3 | AA110: 0 | AB110: =SUM(W110:AA110)-J110 -> 0 | AE110: 0 | AF110: 0 | AG110: 0 | AH110: 0.3 | AI110: 0 | AJ110: =SUM(AE110:AI110)-J110 -> 0 | AN110: =ROUNDUP(V110*J110,0) -> 64 | AQ110: Norte | AR110: =AQ110&" - "&K110 -> Norte - A06
A111: 151S0030EPR | B111: 151S0030 | C111: 151 | D111: 0030 | E111: 151S | F111: S | G111: 151|0030 | H111: RIBEIRÃO CLARO (B) | I111: AC. CACHOEIRA DO ESPÍRITO SANTO | J111: 10.03 | K111: A06 | L111: DER SR3 | O111: 18 | P111: PAV | Q111: BG | R111: CAUQ | S111: 6.6 | T111: 1.2 | U111: 1.3 | V111: 1388 | W111: 0 | X111: 0 | Y111: 2 | Z111: 8.03 | AA111: 0 | AB111: =SUM(W111:AA111)-J111 -> 0 | AE111: 0 | AF111: 0 | AG111: 2 | AH111: 8.03 | AI111: 0 | AJ111: =SUM(AE111:AI111)-J111 -> 0 | AN111: =ROUNDUP(V111*J111,0) -> 13922 | AQ111: Norte | AR111: =AQ111&" - "&K111 -> Norte - A06
A112: 151S0035EPR | B112: 151S0035 | C112: 151 | D112: 0035 | E112: 151S | F112: S | G112: 151|0035 | H112: AC. CACHOEIRA DO ESPÍRITO SANTO | I112: CARLÓPOLIS (A) | J112: 23.63 | K112: A06 | L112: DER SR3 | O112: 18 | P112: PAV | Q112: BG | R112: CAUQ | S112: 6.6 | T112: 1.2 | U112: 0 | V112: 1388 | W112: 0 | X112: 0 | Y112: 2 | Z112: 21.63 | AA112: 0 | AB112: =SUM(W112:AA112)-J112 -> 0 | AE112: 0 | AF112: 0 | AG112: 2 | AH112: 21.63 | AI112: 0 | AJ112: =SUM(AE112:AI112)-J112 -> 0 | AN112: =ROUNDUP(V112*J112,0) -> 32799 | AQ112: Norte | AR112: =AQ112&" - "&K112 -> Norte - A06
A113: 151M0037MUN | B113: 151M0037 | C113: 151 | D113: 0037 | E113: 151M | F113: M | G113: 151|0037 | H113: CARLÓPOLIS (A) | I113: ENTR. PR-218 (PLAN.) (CARLÓPOLIS) | J113: 0.3 | K113: A06 | L113: DER SR3 | O113: 18 | P113: MUN | Q113: BG | R113: CAUQ | S113: 8.2 | T113: 0 | U113: 0 | V113: 327 | W113: 0 | X113: 0 | Y113: 0 | Z113: 0.7 | AA113: 0 | AB113: =SUM(W113:AA113)-J113 -> 0.4 | AE113: =IF(W113=0,0,W113-$AB113) -> 0 | AF113: =IF(X113=0,0,X113-$AB113) -> 0 | AG113: =IF(Y113=0,0,Y113-$AB113) -> 0 | AH113: =IF(Z113=0,0,Z113-$AB113) -> 0.3 | AI113: =IF(AA113=0,0,AA113-$AB113) -> 0 | AJ113: =SUM(AE113:AI113)-J113 -> 0 | AN113: =ROUNDUP(V113*J113,0) -> 99 | AQ113: Norte | AR113: =AQ113&" - "&K113 -> Norte - A06
A114: 151S0044EPR | B114: 151S0044 | C114: 151 | D114: 0044 | E114: 151S | F114: S | G114: 151|0044 | H114: INÍCIO ASFALTO | I114: ALEMOA (FINAL ASFALTO) | J114: 4.85 | K114: A09 | L114: DER SR3 | O114: 21 | P114: PAV | Q114: SE | R114: CAUQ | S114: 6 | T114: 0 | U114: 0 | V114: 66 | W114: 0 | X114: 0 | Y114: 0 | Z114: 4.85 | AA114: 0 | AB114: =SUM(W114:AA114)-J114 -> 0 | AE114: 0 | AF114: 0 | AG114: 0 | AH114: 4.85 | AI114: 0 | AJ114: =SUM(AE114:AI114)-J114 -> 0 | AN114: =ROUNDUP(V114*J114,0) -> 321 | AQ114: Norte | AR114: =AQ114&" - "&K114 -> Norte - A09
A115: 151S0047EPR | B115: 151S0047 | C115: 151 | D115: 0047 | E115: 151S | F115: S | G115: 151|0047 | H115: ENTR. PR-424 (A) (SALTO DO ITARARÉ) | I115: ENTR. PR-424 (B) (AC. SALTO ITARARÉ) | J115: 1.1 | K115: A09 | L115: DER SR3 | O115: 21 | P115: PAV | Q115: SE | R115: CAUQ | S115: 6.3 | T115: 0 | U115: 0 | V115: 2453 | W115: 0 | X115: 0 | Y115: 0 | Z115: 1.1 | AA115: 0 | AB115: =SUM(W115:AA115)-J115 -> 0 | AE115: 0 | AF115: 0 | AG115: 0 | AH115: 1.1 | AI115: 0 | AJ115: =SUM(AE115:AI115)-J115 -> 0 | AN115: =ROUNDUP(V115*J115,0) -> 2699 | AQ115: Norte | AR115: =AQ115&" - "&K115 -> Norte - A09
A116: 151S0075EPR | B116: 151S0075 | C116: 151 | D116: 0075 | E116: 151S | F116: S | G116: 151|0075 | H116: AC. I SANT. DO ITARARÉ | I116: AC. II SANTANA DO ITARARÉ | J116: 1.55 | K116: A01 | L116: DER SR2 | O116: 6 | P116: PAV | Q116: SC | R116: TST | S116: 6.6 | T116: 0 | U116: 0 | V116: 50 | W116: 0 | X116: 0 | Y116: 1 | Z116: 0.55 | AA116: 0 | AB116: =SUM(W116:AA116)-J116 -> 0 | AE116: 0 | AF116: 0 | AG116: 1 | AH116: 0.55 | AI116: 0 | AJ116: =SUM(AE116:AI116)-J116 -> 0 | AN116: =ROUNDUP(V116*J116,0) -> 78 | AQ116: Campos Gerais | AR116: =AQ116&" - "&K116 -> Campos Gerais - A01
A117: 151S0080EPR | B117: 151S0080 | C117: 151 | D117: 0080 | E117: 151S | F117: S | G117: 151|0080 | H117: AC. II SANTANA DO ITARARÉ | I117: ENTR. PR-422 | J117: 24.37 | K117: A01 | L117: DER SR2 | O117: 6 | P117: PAV | Q117: SC | R117: TST | S117: 6.6 | T117: 0 | U117: 0 | V117: 3056 | W117: 0 | X117: 0 | Y117: 0 | Z117: 24.37 | AA117: 0 | AB117: =SUM(W117:AA117)-J117 -> 0 | AE117: 0 | AF117: 0 | AG117: 0 | AH117: 24.37 | AI117: 0 | AJ117: =SUM(AE117:AI117)-J117 -> 0 | AN117: =ROUNDUP(V117*J117,0) -> 74475 | AQ117: Campos Gerais | AR117: =AQ117&" - "&K117 -> Campos Gerais - A01
A118: 151S0090EPR | B118: 151S0090 | C118: 151 | D118: 0090 | E118: 151S | F118: S | G118: 151|0090 | H118: ENTR. PR-422 | I118: SÃO JOSÉ DA BOA VISTA (A) | J118: 11.05 | K118: A01 | L118: DER SR2 | O118: 6 | P118: PAV | Q118: SC | R118: TSD | S118: 6.6 | T118: 0 | U118: 0 | V118: 1927 | W118: 0 | X118: 2 | Y118: 4 | Z118: 5.05 | AA118: 0 | AB118: =SUM(W118:AA118)-J118 -> 0 | AE118: 0 | AF118: 2 | AG118: 4 | AH118: 5.05 | AI118: 0 | AJ118: =SUM(AE118:AI118)-J118 -> 0 | AN118: =ROUNDUP(V118*J118,0) -> 21294 | AQ118: Campos Gerais | AR118: =AQ118&" - "&K118 -> Campos Gerais - A01
A119: 151S0270EPR | B119: 151S0270 | C119: 151 | D119: 0270 | E119: 151S | F119: S | G119: 151|0270 | H119: ENTR. PRC-373 (A) (P. GROSSA) | I119: P. GROSSA (ARROIO F. ROCHA) (A) | J119: 5.24 | K119: A02 | L119: DER SR2 | O119: 7 | P119: PAV | Q119: SC | R119: CAUQ | S119: 7 | T119: 1 | U119: 0 | V119: 7858 | W119: 0 | X119: 0 | Y119: 0.24 | Z119: 5 | AA119: 0 | AB119: =SUM(W119:AA119)-J119 -> 0 | AE119: 0 | AF119: 0 | AG119: 0.24 | AH119: 5 | AI119: 0 | AJ119: =SUM(AE119:AI119)-J119 -> 0 | AN119: =ROUNDUP(V119*J119,0) -> 41176 | AQ119: Campos Gerais | AR119: =AQ119&" - "&K119 -> Campos Gerais - A02
A120: 151S0310EPR | B120: 151S0310 | C120: 151 | D120: 0310 | E120: 151S | F120: S | G120: 151|0310 | H120: ENTR. BR-376 (PONTA GROSSA) (B) | I120: AC. AEROPORTO P. GROSSA | J120: 4.83 | K120: A02 | L120: DER SR2 | O120: 7 | P120: PAV | Q120: BG | R120: CAUQ | S120: 6.6 | T120: 0 | U120: 0 | V120: 5618 | W120: 0 | X120: 1 | Y120: 2 | Z120: 1.83 | AA120: 0 | AB120: =SUM(W120:AA120)-J120 -> 0 | AE120: 0 | AF120: 1 | AG120: 2 | AH120: 1.83 | AI120: 0 | AJ120: =SUM(AE120:AI120)-J120 -> 0 | AN120: =ROUNDUP(V120*J120,0) -> 27135 | AQ120: Campos Gerais | AR120: =AQ120&" - "&K120 -> Campos Gerais - A02
A121: 151S0315EPR | B121: 151S0315 | C121: 151 | D121: 0315 | E121: 151S | F121: S | G121: 151|0315 | H121: AC. AEROPORTO P. GROSSA | I121: ENTR. PR-438 (P/ TEIXEIRA SOARES) | J121: 1.97 | K121: A02 | L121: DER SR2 | O121: 7 | P121: PAV | Q121: BG | R121: CAUQ | S121: 6.6 | T121: 0 | U121: 0 | V121: 2381 | W121: 0 | X121: 0 | Y121: 1 | Z121: 0.97 | AA121: 0 | AB121: =SUM(W121:AA121)-J121 -> 0 | AE121: 0 | AF121: 0 | AG121: 1 | AH121: 0.97 | AI121: 0 | AJ121: =SUM(AE121:AI121)-J121 -> 0 | AN121: =ROUNDUP(V121*J121,0) -> 4691 | AQ121: Campos Gerais | AR121: =AQ121&" - "&K121 -> Campos Gerais - A02
A122: 151S0320EPR | B122: 151S0320 | C122: 151 | D122: 0320 | E122: 151S | F122: S | G122: 151|0320 | H122: ENTR. PR-438 (P/ TEIXEIRA SOARES) | I122: RIO CANIÚ | J122: 15.49 | K122: A02 | L122: DER SR2 | O122: 7 | P122: PAV | Q122: BG | R122: CAUQ | S122: 6.6 | T122: 0.6 | U122: 0 | V122: 3291 | W122: 0 | X122: 3 | Y122: 3.49 | Z122: 9 | AA122: 0 | AB122: =SUM(W122:AA122)-J122 -> 0 | AE122: 0 | AF122: 3 | AG122: 3.49 | AH122: 9 | AI122: 0 | AJ122: =SUM(AE122:AI122)-J122 -> 0 | AN122: =ROUNDUP(V122*J122,0) -> 50978 | AQ122: Campos Gerais | AR122: =AQ122&" - "&K122 -> Campos Gerais - A02
A123: 151S0330EPR | B123: 151S0330 | C123: 151 | D123: 0330 | E123: 151S | F123: S | G123: 151|0330 | H123: RIO CANIÚ | I123: AC. PALMEIRA | J123: 15.2 | K123: A02 | L123: DER SR2 | O123: 7 | P123: PAV | Q123: SC | R123: CAUQ | S123: 6.6 | T123: 0 | U123: 0 | V123: 3580 | W123: 0 | X123: 2 | Y123: 5.2 | Z123: 8 | AA123: 0 | AB123: =SUM(W123:AA123)-J123 -> 0 | AE123: 0 | AF123: 2 | AG123: 5.2 | AH123: 8 | AI123: 0 | AJ123: =SUM(AE123:AI123)-J123 -> 0 | AN123: =ROUNDUP(V123*J123,0) -> 54416 | AQ123: Campos Gerais | AR123: =AQ123&" - "&K123 -> Campos Gerais - A02
A124: 151S0350EPR | B124: 151S0350 | C124: 151 | D124: 0350 | E124: 151S | F124: S | G124: 151|0350 | H124: AC. PALMEIRA | I124: ENTR. BR-277 | J124: 2.62 | K124: A02 | L124: DER SR2 | O124: 7 | P124: PAV | Q124: BG | R124: CAUQ | S124: 6.6 | T124: 0 | U124: 0 | V124: 3580 | W124: 1 | X124: 0 | Y124: 1.62 | Z124: 0 | AA124: 0 | AB124: =SUM(W124:AA124)-J124 -> 0 | AE124: 1 | AF124: 0 | AG124: 1.62 | AH124: 0 | AI124: 0 | AJ124: =SUM(AE124:AI124)-J124 -> 0 | AN124: =ROUNDUP(V124*J124,0) -> 9380 | AQ124: Campos Gerais | AR124: =AQ124&" - "&K124 -> Campos Gerais - A02
A125: 151S0370EPR | B125: 151S0370 | C125: 151 | D125: 0370 | E125: 151S | F125: S | G125: 151|0370 | H125: ENTR. BR-277 | I125: AC. SÃO JOÃO DO TRIUNFO | J125: 46.48 | K125: A04 | L125: DER SR1 | O125: 4 | P125: PAV | Q125: MH | R125: CAUQ | S125: 6.6 | T125: 0.7 | U125: 0 | V125: 6022 | W125: 0 | X125: 5 | Y125: 20 | Z125: 21.48 | AA125: 0 | AB125: =SUM(W125:AA125)-J125 -> 0 | AE125: 0 | AF125: 5 | AG125: 20 | AH125: 21.48 | AI125: 0 | AJ125: =SUM(AE125:AI125)-J125 -> 0 | AN125: =ROUNDUP(V125*J125,0) -> 279903 | AQ125: Leste | AR125: =AQ125&" - "&K125 -> Leste - A04
A126: 151S0390EPR | B126: 151S0390 | C126: 151 | D126: 0390 | E126: 151S | F126: S | G126: 151|0390 | H126: AC. SÃO JOÃO DO TRIUNFO | I126: SÃO MATEUS DO SUL (A) | J126: 27.47 | K126: A04 | L126: DER SR1 | O126: 4 | P126: PAV | Q126: BG | R126: CAUQ | S126: 6.6 | T126: 1.2 | U126: 0 | V126: 3986 | W126: 0 | X126: 3 | Y126: 7 | Z126: 17.47 | AA126: 0 | AB126: =SUM(W126:AA126)-J126 -> 0 | AE126: 0 | AF126: 3 | AG126: 7 | AH126: 17.47 | AI126: 0 | AJ126: =SUM(AE126:AI126)-J126 -> 0 | AN126: =ROUNDUP(V126*J126,0) -> 109496 | AQ126: Leste | AR126: =AQ126&" - "&K126 -> Leste - A04
A127: 151M0395MUN | B127: 151M0395 | C127: 151 | D127: 0395 | E127: 151M | F127: M | G127: 151|0395 | H127: SÃO MATEUS DO SUL (A) | I127: ENTR. PR-364 (S. MATEUS DO SUL) (B) | J127: 1.67 | K127: A04 | L127: DER SR1 | O127: 4 | P127: MUN | Q127: BG | R127: CAUQ | S127: 12.25 | T127: 0 | U127: 0 | V127: 796 | W127: 0 | X127: 0 | Y127: 0 | Z127: 1.67 | AA127: 0 | AB127: =SUM(W127:AA127)-J127 -> 0 | AE127: 0 | AF127: 0 | AG127: 0 | AH127: 1.67 | AI127: 0 | AJ127: =SUM(AE127:AI127)-J127 -> 0 | AN127: =ROUNDUP(V127*J127,0) -> 1330 | AQ127: Leste | AR127: =AQ127&" - "&K127 -> Leste - A04
A128: 151S0400EPR | B128: 151S0400 | C128: 151 | D128: 0400 | E128: 151S | F128: S | G128: 151|0400 | H128: ENTR. PR-364 (S. MATEUS DO SUL) (B) | I128: ENTR. BR-476 (A) | J128: 0.51 | K128: A04 | L128: DER SR1 | O128: 4 | P128: PAV | Q128: BG | R128: CAUQ | S128: 6.6 | T128: 1.2 | U128: 0 | V128: 3668 | W128: 0 | X128: 0 | Y128: 0 | Z128: 0.51 | AA128: 0 | AB128: =SUM(W128:AA128)-J128 -> 0 | AE128: 0 | AF128: 0 | AG128: 0 | AH128: 0.51 | AI128: 0 | AJ128: =SUM(AE128:AI128)-J128 -> 0 | AN128: =ROUNDUP(V128*J128,0) -> 1871 | AQ128: Leste | AR128: =AQ128&" - "&K128 -> Leste - A04
A129: 151S0430EPR | B129: 151S0430 | C129: 151 | D129: 0430 | E129: 151S | F129: S | G129: 151|0430 | H129: ENTR. BR-476 (B) | I129: LAJEADO | J129: 11.87 | K129: A04 | L129: DER SR1 | O129: 4 | P129: PAV | Q129: BG | R129: CAUQ | S129: 7.87 | T129: 0 | U129: 0 | V129: 2721 | W129: 0 | X129: 0 | Y129: 2 | Z129: 9.87 | AA129: 0 | AB129: =SUM(W129:AA129)-J129 -> 0 | AE129: 0 | AF129: 0 | AG129: 2 | AH129: 9.87 | AI129: 0 | AJ129: =SUM(AE129:AI129)-J129 -> 0 | AN129: =ROUNDUP(V129*J129,0) -> 32299 | AQ129: Leste | AR129: =AQ129&" - "&K129 -> Leste - A04
A130: 151S0440EPR | B130: 151S0440 | C130: 151 | D130: 0440 | E130: 151S | F130: S | G130: 151|0440 | H130: LAJEADO | I130: OLHO D'ÁGUA | J130: 10.28 | K130: A04 | L130: DER SR1 | O130: 4 | P130: PAV | Q130: BG | R130: CAUQ | S130: 7.87 | T130: 0 | U130: 0 | V130: 1193 | W130: 0 | X130: 0 | Y130: 0 | Z130: 10.28 | AA130: 0 | AB130: =SUM(W130:AA130)-J130 -> 0 | AE130: 0 | AF130: 0 | AG130: 0 | AH130: 10.28 | AI130: 0 | AJ130: =SUM(AE130:AI130)-J130 -> 0 | AN130: =ROUNDUP(V130*J130,0) -> 12265 | AQ130: Leste | AR130: =AQ130&" - "&K130 -> Leste - A04
A131: 151S0450EPR | B131: 151S0450 | C131: 151 | D131: 0450 | E131: 151S | F131: S | G131: 151|0450 | H131: OLHO D'ÁGUA | I131: DIVISA PR/SC (TRÊS BARRAS) | J131: 3.7 | K131: A04 | L131: DER SR1 | O131: 4 | P131: PAV | Q131: BG | R131: CAUQ | S131: 7.87 | T131: 0 | U131: 0 | V131: 1193 | W131: 0 | X131: 0 | Y131: 0 | Z131: 3.7 | AA131: 0 | AB131: =SUM(W131:AA131)-J131 -> 0 | AE131: 0 | AF131: 0 | AG131: 0 | AH131: 3.7 | AI131: 0 | AJ131: =SUM(AE131:AI131)-J131 -> 0 | AN131: =ROUNDUP(V131*J131,0) -> 4415 | AQ131: Leste | AR131: =AQ131&" - "&K131 -> Leste - A04
A132: 158M0045MUN | B132: 158M0045 | C132: 158 | D132: 0045 | E132: 158M | F132: M | G132: 158|0045 | H132: ENTR. PR-494/556 (PLAN.) (S. JOÃO DO CAIUÁ) (A) | I132: SÃO JOÃO DO CAIUÁ (B) | J132: 0.47 | K132: A04 | L132: DER SR4 | O132: 26 | P132: MUN | Q132: SE | R132: TSD | S132: 11 | T132: 0 | U132: 0 | V132: 780 | W132: 0 | X132: 0 | Y132: 0 | Z132: 0.47 | AA132: 0 | AB132: =SUM(W132:AA132)-J132 -> 0 | AE132: 0 | AF132: 0 | AG132: 0 | AH132: 0.47 | AI132: 0 | AJ132: =SUM(AE132:AI132)-J132 -> 0 | AN132: =ROUNDUP(V132*J132,0) -> 367 | AQ132: Noroeste | AR132: =AQ132&" - "&K132 -> Noroeste - A04
A133: 158S0050PRC | B133: 158S0050 | C133: 158 | D133: 0050 | E133: 158S | F133: S | G133: 158|0050 | H133: SÃO JOÃO DO CAIUÁ (B) | I133: SUMARÉ | J133: 26.72 | K133: A04 | L133: DER SR4 | O133: 26 | P133: PAV | Q133: SE | R133: TSD | S133: 6 | T133: 0.5 | U133: 0 | V133: 1370 | W133: 0 | X133: 2.72 | Y133: 7 | Z133: 17 | AA133: 0 | AB133: =SUM(W133:AA133)-J133 -> 0 | AE133: 0 | AF133: 2.72 | AG133: 7 | AH133: 17 | AI133: 0 | AJ133: =SUM(AE133:AI133)-J133 -> 0 | AN133: =ROUNDUP(V133*J133,0) -> 36607 | AQ133: Noroeste | AR133: =AQ133&" - "&K133 -> Noroeste - A04
A134: 158S0055PRC | B134: 158S0055 | C134: 158 | D134: 0055 | E134: 158S | F134: S | G134: 158|0055 | H134: SUMARÉ | I134: ENTR. BR-376 (A) (SUMARÉ) | J134: 2.24 | K134: A04 | L134: DER SR4 | O134: 26 | P134: PAV | Q134: SE | R134: CAUQ | S134: 6.6 | T134: 0 | U134: 0 | V134: 1026 | W134: 0 | X134: 0 | Y134: 1 | Z134: 1.24 | AA134: 0 | AB134: =SUM(W134:AA134)-J134 -> 0 | AE134: 0 | AF134: 0 | AG134: 1 | AH134: 1.24 | AI134: 0 | AJ134: =SUM(AE134:AI134)-J134 -> 0 | AN134: =ROUNDUP(V134*J134,0) -> 2299 | AQ134: Noroeste | AR134: =AQ134&" - "&K134 -> Noroeste - A04
A135: 158S0070PRC | B135: 158S0070 | C135: 158 | D135: 0070 | E135: 158S | F135: S | G135: 158|0070 | H135: ENTR. BR-376 (B) | I135: ENTR. PR-492 (TAMBOARA) | J135: 13.63 | K135: A07 | L135: DER SR4 | O135: 29 | P135: PAV | Q135: SMC | R135: CAUQ | S135: 7 | T135: 2.5 | U135: 0 | V135: 1696 | W135: 0 | X135: 0 | Y135: 5 | Z135: 8.63 | AA135: 0 | AB135: =SUM(W135:AA135)-J135 -> 0 | AE135: 0 | AF135: 0 | AG135: 5 | AH135: 8.63 | AI135: 0 | AJ135: =SUM(AE135:AI135)-J135 -> 0 | AN135: =ROUNDUP(V135*J135,0) -> 23117 | AQ135: Noroeste | AR135: =AQ135&" - "&K135 -> Noroeste - A07
A136: 158S0100PRC | B136: 158S0100 | C136: 158 | D136: 0100 | E136: 158S | F136: S | G136: 158|0100 | H136: ENTR PR-317/465 (PEABIRÚ) | I136: AC. PEABIRU (AV. VILA RICA) | J136: 3.06 | K136: A05 | L136: DER SR4 | O136: 27 | P136: PAV | Q136: BG | R136: CAUQ | S136: 7.2 | T136: 2.5 | U136: 0 | V136: 3538 | W136: 0 | X136: 0 | Y136: 0 | Z136: 3.06 | AA136: 0 | AB136: =SUM(W136:AA136)-J136 -> 0 | AE136: 0 | AF136: 0 | AG136: 0 | AH136: 3.06 | AI136: 0 | AJ136: =SUM(AE136:AI136)-J136 -> 0 | AN136: =ROUNDUP(V136*J136,0) -> 10827 | AQ136: Noroeste | AR136: =AQ136&" - "&K136 -> Noroeste - A05
A137: 158S0110PRC | B137: 158S0110 | C137: 158 | D137: 0110 | E137: 158S | F137: S | G137: 158|0110 | H137: AC. PEABIRU (AV. VILA RICA) | I137: INÍCIO PISTA DUPLA | J137: 2.48 | K137: A05 | L137: DER SR4 | O137: 27 | P137: PAV | Q137: BG | R137: CAUQ | S137: 7.2 | T137: 2.5 | U137: 0 | V137: 3538 | W137: 0 | X137: 0 | Y137: 0 | Z137: 2.48 | AA137: 0 | AB137: =SUM(W137:AA137)-J137 -> 0 | AE137: 0 | AF137: 0 | AG137: 0 | AH137: 2.48 | AI137: 0 | AJ137: =SUM(AE137:AI137)-J137 -> 0 | AN137: =ROUNDUP(V137*J137,0) -> 8775 | AQ137: Noroeste | AR137: =AQ137&" - "&K137 -> Noroeste - A05
A138: 158S0200PRC | B138: 158S0200 | C138: 158 | D138: 0200 | E138: 158S | F138: S | G138: 158|0200 | H138: ENTR BR-277 (LARANJEIRAS DO SUL) | I138: AC. LARANJEIRAS DO SUL | J138: 2.12 | K138: A07 | L138: DER SR2 | O138: 12 | P138: PAV | Q138: BG | R138: CAUQ | S138: 7 | T138: 1.5 | U138: 0 | V138: 4192 | W138: 0 | X138: 0 | Y138: 0 | Z138: 2.12 | AA138: 0 | AB138: =SUM(W138:AA138)-J138 -> 0 | AE138: 0 | AF138: 0 | AG138: 0 | AH138: 2.12 | AI138: 0 | AJ138: =SUM(AE138:AI138)-J138 -> 0 | AN138: =ROUNDUP(V138*J138,0) -> 8888 | AQ138: Campos Gerais | AR138: =AQ138&" - "&K138 -> Campos Gerais - A07
... A150: 158M0357MUN | B150: 158M0357 | C150: 158 | D150: 0357 | E150: 158M | F150: M | G150: 158|0357 | H150: ENTR. PR-562 (PLAN.) (CORONEL VIVIDA) | I150: AC. SECUND. CEL. VIVIDA (B) | J150: 1.13 | K150: A07 | L150: DER SR5 | O150: 39 | P150: MUN | Q150: BG | R150: CAUQ | S150: 12 | T150: 0 | U150: 0 | V150: 424 | W150: 0 | X150: 0 | Y150: 1.13 | Z150: 0 | AA150: 0 | AB150: =SUM(W150:AA150)-J150 -> 0 | AE150: 0 | AF150: 0 | AG150: 1.13 | AH150: 0 | AI150: 0 | AJ150: =SUM(AE150:AI150)-J150 -> 0 | AN150: =ROUNDUP(V150*J150,0) -> 480 | AQ150: Oeste | AR150: =AQ150&" - "&K150 -> Oeste - A07
A151: 158S0420PRC | B151: 158S0420 | C151: 158 | D151: 0420 | E151: 158S | F151: S | G151: 158|0420 | H151: ENTR. PRC-280 (B) | I151: AC. OESTE VITORINO | J151: 1.04 | K151: A08 | L151: DER SR5 | N151: =O151 -> 40 | O151: 40 | P151: PAV | Q151: BG | R151: CAUQ | S151: 7.85 | T151: 0 | U151: 0 | V151: 1994 | W151: 0 | X151: 0 | Y151: 1.04 | Z151: 0 | AA151: 0 | AB151: =SUM(W151:AA151)-J151 -> 0 | AE151: 0 | AF151: 0 | AG151: 1.04 | AH151: 0 | AI151: 0 | AJ151: =SUM(AE151:AI151)-J151 -> 0 | AN151: =ROUNDUP(V151*J151,0) -> 2074 | AQ151: Oeste | AR151: =AQ151&" - "&K151 -> Oeste - A08
A152: 158S0430PRC | B152: 158S0430 | C152: 158 | D152: 0430 | E152: 158S | F152: S | G152: 158|0430 | H152: AC. OESTE VITORINO | I152: DIV. PR/SC (S. LOURENÇO DO OESTE) | J152: 12.09 | K152: A08 | L152: DER SR5 | N152: =O152 -> 40 | O152: 40 | P152: PAV | Q152: BG | R152: CAUQ | S152: 7.2 | T152: 0 | U152: 0 | V152: 5103 | W152: 0 | X152: 0 | Y152: 4.09 | Z152: 8 | AA152: 0 | AB152: =SUM(W152:AA152)-J152 -> 0 | AE152: 0 | AF152: 0 | AG152: 4.09 | AH152: 8 | AI152: 0 | AJ152: =SUM(AE152:AI152)-J152 -> 0 | AN152: =ROUNDUP(V152*J152,0) -> 61696 | AQ152: Oeste | AR152: =AQ152&" - "&K152 -> Oeste - A08
A153: 160S0020EPR | B153: 160S0020 | C153: 160 | D153: 0020 | E153: 160S | F153: S | G153: 160|0020 | H153: PARANAGI | I153: ENTR. PR-323 (MAIRIPORÃ) | J153: 11.96 | K153: A04 | L153: DER SR3 | O153: 16 | P153: PAV | Q153: SMC | R153: CAUQ | S153: 6.2 | T153: 0 | U153: 0 | V153: 529 | W153: 0 | X153: 8 | Y153: 3.96 | Z153: 0 | AA153: 0 | AB153: =SUM(W153:AA153)-J153 -> 0 | AE153: 0 | AF153: 8 | AG153: 3.96 | AH153: 0 | AI153: 0 | AJ153: =SUM(AE153:AI153)-J153 -> 0 | AN153: =ROUNDUP(V153*J153,0) -> 6327 | AQ153: Norte | AR153: =AQ153&" - "&K153 -> Norte - A04
A154: 160S0030EPR | B154: 160S0030 | C154: 160 | D154: 0030 | E154: 160S | F154: S | G154: 160|0030 | H154: ENTR. PR-323 (MAIRIPORÃ) | I154: ENTR. PR-443 | J154: 4.94 | K154: A04 | L154: DER SR3 | O154: 16 | P154: PAV | Q154: BG | R154: CAUQ | S154: 6.6 | T154: 1 | U154: 0 | V154: 3347 | W154: 0 | X154: 0 | Y154: 0 | Z154: 4.94 | AA154: 0 | AB154: =SUM(W154:AA154)-J154 -> 0 | AE154: 0 | AF154: 0 | AG154: 0 | AH154: 4.94 | AI154: 0 | AJ154: =SUM(AE154:AI154)-J154 -> 0 | AN154: =ROUNDUP(V154*J154,0) -> 16535 | AQ154: Norte | AR154: =AQ154&" - "&K154 -> Norte - A04
A155: 160S0050EPR | B155: 160S0050 | C155: 160 | D155: 0050 | E155: 160S | F155: S | G155: 160|0050 | H155: ENTR. PR-443 | I155: ACESSO SERTANEJA | J155: 6.79 | K155: A04 | L155: DER SR3 | O155: 16 | P155: PAV | Q155: BG | R155: CAUQ | S155: 6.6 | T155: 1 | U155: 0 | V155: 3347 | W155: 0 | X155: 0 | Y155: 0 | Z155: 6.79 | AA155: 0 | AB155: =SUM(W155:AA155)-J155 -> 0 | AE155: 0 | AF155: 0 | AG155: 0 | AH155: 6.79 | AI155: 0 | AJ155: =SUM(AE155:AI155)-J155 -> 0 | AN155: =ROUNDUP(V155*J155,0) -> 22727 | AQ155: Norte | AR155: =AQ155&" - "&K155 -> Norte - A04
A156: 160S0070EPR | B156: 160S0070 | C156: 160 | D156: 0070 | E156: 160S | F156: S | G156: 160|0070 | H156: ACESSO SERTANEJA | I156: ACESSO LEÓPOLIS | J156: 7.55 | K156: A04 | L156: DER SR3 | O156: 16 | P156: PAV | Q156: BG | R156: CAUQ | S156: 6.6 | T156: 1 | U156: 0 | V156: 3347 | W156: 0 | X156: 0 | Y156: 0 | Z156: 7.55 | AA156: 0 | AB156: =SUM(W156:AA156)-J156 -> 0 | AE156: 0 | AF156: 0 | AG156: 0 | AH156: 7.55 | AI156: 0 | AJ156: =SUM(AE156:AI156)-J156 -> 0 | AN156: =ROUNDUP(V156*J156,0) -> 25270 | AQ156: Norte | AR156: =AQ156&" - "&K156 -> Norte - A04
A157: 160S0090EPR | B157: 160S0090 | C157: 160 | D157: 0090 | E157: 160S | F157: S | G157: 160|0090 | H157: ACESSO LEÓPOLIS | I157: AC. SECUNDÁRIO LEÓPOLIS | J157: 0.69 | K157: A04 | L157: DER SR3 | O157: 16 | P157: PAV | Q157: BG | R157: CAUQ | S157: 6.6 | T157: 1 | U157: 0 | V157: 3347 | W157: 0 | X157: 0 | Y157: 0 | Z157: 0.69 | AA157: 0 | AB157: =SUM(W157:AA157)-J157 -> 0 | AE157: 0 | AF157: 0 | AG157: 0 | AH157: 0.69 | AI157: 0 | AJ157: =SUM(AE157:AI157)-J157 -> 0 | AN157: =ROUNDUP(V157*J157,0) -> 2310 | AQ157: Norte | AR157: =AQ157&" - "&K157 -> Norte - A04
A158: 160S0095EPR | B158: 160S0095 | C158: 160 | D158: 0095 | E158: 160S | F158: S | G158: 160|0095 | H158: AC. SECUNDÁRIO LEÓPOLIS | I158: AC. CORNÉLIO PROCÓPIO | J158: 15.29 | K158: A04 | L158: DER SR3 | O158: 16 | P158: PAV | Q158: BG | R158: CAUQ | S158: 6.6 | T158: 1 | U158: 0 | V158: 2816 | W158: 0 | X158: 0 | Y158: 1 | Z158: 14.29 | AA158: 0 | AB158: =SUM(W158:AA158)-J158 -> 0 | AE158: 0 | AF158: 0 | AG158: 1 | AH158: 14.29 | AI158: 0 | AJ158: =SUM(AE158:AI158)-J158 -> 0 | AN158: =ROUNDUP(V158*J158,0) -> 43057 | AQ158: Norte | AR158: =AQ158&" - "&K158 -> Norte - A04
...

Sheet IDHM (IBGE2022)
A1: Paraná | Todos os Municípios (IBGE 2022)
A3: Município [-] | B3: Código [-] | C3: Gentílico [-] | D3: Prefeito [2025] | E3: Área Territorial - km² [2025] | F3: População no último censo - pessoas [2022] | G3: Densidade demográfica - hab/km² [2022] | H3: População estimada - pessoas [2025] | I3: Escolarização <span>6 a 14 anos</span> - % [2022] | J3: IDHM <span>Índice de desenvolvimento humano municipal</span> [2010] | K3: Mortalidade infantil - óbitos por mil nascidos vivos [2023] | L3: Total de receitas brutas realizadas - R$ [2023] | M3: Total de despesas brutas empenhadas - R$ [2023] | N3: PIB per capita - R$ [2023]
A4: Abatiá | B4: 4100103 | C4: abatiense | D4: SONIA APARECIDA DE SOUZA CHAVES | E4: 227.923 | F4: 7241 | G4: 31.66 | H4: 7233 | I4: 94.88 | J4: 0.687 | K4: - | L4: 48184402 | M4: 40393404 | N4: 41039.39
A5: Adrianópolis | B5: 4100202 | C5: adrianopolitano ou adrianopolense | D5: VANDIR DE OLIVEIRA ROSA | E5: 1343.898 | F5: 6256 | G5: 4.64 | H5: 6319 | I5: 99.64 | J5: 0.667 | K5: - | L5: 65885672 | M5: 60528117 | N5: 74669
A6: Agudos do Sul | B6: 4100301 | C6: agudense-do-sul ou agudense | D6: GENEZIO GONÇALVES DA LUZ | E6: 191.336 | F6: 10233 | G6: 53.22 | H6: 10770 | I6: 98.51 | J6: 0.66 | K6: 29.85 | L6: 56439846 | M6: 48989316 | N6: 27302.69
A7: Almirante Tamandaré | B7: 4100400 | C7: tamandareense | D7: CAMILO DANIEL LOVATO | E7: 193.736 | F7: 119825 | G7: 616.93 | H7: 125861 | I7: 98.36 | J7: 0.699 | K7: 6.57 | L7: 4.6981431e+08 | M7: 4.3286764e+08 | N7: 18715.79
A8: Altamira do Paraná | B8: 4100459 | C8: altamirense | D8: ELZA APARECIDA DA SILVA | E8: 386.952 | F8: 3590 | G8: 9.28 | H8: 3496 | I8: 99.6 | J8: 0.667 | K8: 21.28 | L8: 46198534 | M8: 43168730 | N8: 32175.22
A9: Altônia | B9: 4100509 | C9: altoniano | D9: DIEGO JARDIM PERGO | E9: 663.955 | F9: 18742 | G9: 28.33 | H9: 18634 | I9: 98.08 | J9: 0.721 | K9: 4.9 | L9: 1.2844817e+08 | M9: 1.2452387e+08 | N9: 29153.82
A10: Alto Paraná | B10: 4100608 | C10: alto-paranaense | D10: CLAUDEMIR JOIA PEREIRA | E10: 409.014 | F10: 13909 | G10: 34.11 | H10: 14183 | I10: 99.69 | J10: 0.696 | K10: 24.84 | L10: 98195545 | M10: 97629840 | N10: 40453.42
A11: Alto Piquiri | B11: 4100707 | C11: alto-piquirense | D11: GIOVANE MENDES DE CARVALHO | E11: 448.373 | F11: 9727 | G11: 21.73 | H11: 9771 | I11: 99.04 | J11: 0.676 | K11: 16 | L11: 72062780 | M11: 64639205 | N11: 50230.67
A12: Alvorada do Sul | B12: 4100806 | C12: alvoradense-do-sul | D12: MARCOS ANTONIO GASPARELLI | E12: 424.25 | F12: 10326 | G12: 24.34 | H12: 10481 | I12: 99.3 | J12: 0.708 | K12: 10.53 | L12: 98949999 | M12: 98055610 | N12: 42266.4
A13: Amaporã | B13: 4100905 | C13: amaporense | D13: MARCOS MARIN | E13: 384.91 | F13: 4762 | G13: 12.38 | H13: 4688 | I13: 97.91 | J13: 0.669 | K13: - | L13: 58267630 | M13: 51115529 | N13: 34418.01
A14: Ampére | B14: 4101002 | C14: amperense | D14: DOUGLAS DIEMS MOROCKOSKI POTRICH | E14: 297.174 | F14: 19620 | G14: 65.76 | H14: 20337 | I14: 94.47 | J14: 0.709 | K14: 18.12 | L14: 1.3446431e+08 | M14: 1.2172678e+08 | N14: 51028.26
A15: Anahy | B15: 4101051 | C15: anaiense | D15: ARILSON BATISTA DE SOUZA | E15: 104.09 | F15: 2918 | G15: 28.36 | H15: 2971 | I15: 98.9 | J15: 0.695 | K15: 96.77 | L15: 42860517 | M15: 38037549 | N15: 42605.49
A16: Andirá | B16: 4101101 | C16: andiraense | D16: EDNYRA APARECIDA SANCHES BUENO DE GODOY FERREIRA | E16: 234.635 | F16: 19878 | G16: 84.25 | H16: 19989 | I16: 99.54 | J16: 0.725 | K16: 9.17 | L16: 1.4074397e+08 | M16: 1.4062558e+08 | N16: 43322.9
A17: Ângulo | B17: 4101150 | C17: angulense | D17: ALEXANDRE DE SOUSA PROFETA | E17: 106.021 | F17: 3235 | G17: 30.51 | H17: 3357 | I17: 100 | J17: 0.721 | K17: 25.64 | L17: 48566440 | M17: 48971722 | N17: 55572.79
A18: Antonina | B18: 4101200 | C18: antoninense | D18: ROZANE MARISTELA BENEDETTI OSAKI | E18: 890.065 | F18: 18091 | G18: 20.29 | H18: 18140 | I18: 99.12 | J18: 0.687 | K18: 20.62 | L18: 1.5878553e+08 | M18: 1.5102849e+08 | N18: 55368.68
A19: Antônio Olinto | B19: 4101309 | C19: antoniolintense | D19: FABIO STANISZEWSKI MACHIAVELLI | E19: 463.694 | F19: 7018 | G19: 14.94 | H19: 7048 | I19: 99.59 | J19: 0.656 | K19: 14.49 | L19: 50575449 | M19: 49357482 | N19: 40269.4
A20: Apucarana | B20: 4101408 | C20: apucaranense | D20: RODOLFO MOTA DA SILVA | E20: 556.771 | F20: 130134 | G20: 233.64 | H20: 134910 | I20: 99.57 | J20: 0.748 | K20: 9.68 | L20: 6.8756598e+08 | M20: 652889778 | N20: 37146.42
A21: Arapongas | B21: 4101507 | C21: araponguense | D21: RAFAEL FELIPE CITA | E21: 383.37 | F21: 119138 | G21: 311.7 | H21: 124838 | I21: 96.34 | J21: 0.748 | K21: 11.5 | L21: 7.7087305e+08 | M21: 6.6899856e+08 | N21: 47973.54
A22: Arapoti | B22: 4101606 | C22: arapotiense | D22: IRANI JOSE BARROS | E22: 1363.843 | F22: 25777 | G22: 18.98 | H22: 26325 | I22: 99.38 | J22: 0.723 | K22: 19.83 | L22: 1.9017142e+08 | M22: 1.6137375e+08 | N22: 63347.91
A23: Arapuã | B23: 4101655 | C23: arapuense | D23: MANOEL SALVADOR | E23: 217.599 | F23: 3527 | G23: 16.23 | H23: 3573 | I23: 100 | J23: 0.676 | K23: 23.81 | L23: 43140389 | M23: 37505508 | N23: 43743.99
A24: Araruna | B24: 4101705 | C24: ararunense | D24: GUSTAVO FRANÇA DOS SANTOS | E24: 492.521 | F24: 14485 | G24: 29.37 | H24: 14894 | I24: 99.36 | J24: 0.704 | K24: 17.65 | L24: 1.016425e+08 | M24: 89235336 | N24: 43548.25
A25: Araucária | B25: 4101804 | C25: araucariano | D25: LUIZ GUSTAVO BOTOGOSKI | E25: 469.549 | F25: 151666 | G25: 323.22 | H25: 162247 | I25: 99.26 | J25: 0.74 | K25: 9.46 | L25: 2.0188287e+09 | M25: 1.7655351e+09 | N25: 224671.66
A26: Ariranha do Ivaí | B26: 4101853 | C26: ariranhense do ivaí | D26: THIAGO EPIFANIO DA SILVA | E26: 236.039 | F26: 2329 | G26: 9.95 | H26: 2351 | I26: 100 | J26: 0.67 | K26: 35.71 | L26: 42855937 | M26: 38805906 | N26: 62246.84
A27: Assaí | B27: 4101903 | C27: assaiense | D27: MICHEL ANGELO BOMTEMPO | E27: 440.347 | F27: 13797 | G27: 31.33 | H27: 13477 | I27: 97.56 | J27: 0.728 | K27: - | L27: 1.0668729e+08 | M27: 93803568 | N27: 46183.5
A28: Assis Chateaubriand | B28: 4102000 | C28: assis-chateaubriense | D28: MARCEL HENRIQUE MICHELETTO | E28: 980.816 | F28: 36808 | G28: 37.53 | H28: 38357 | I28: 99.74 | J28: 0.729 | K28: 13.73 | L28: 2.6137416e+08 | M28: 2.2922134e+08 | N28: 55252.41
A29: Astorga | B29: 4102109 | C29: astorgano | D29: SUZIE APARECIDA PUCILLO ZANATTA | E29: 435.21 | F29: 25475 | G29: 58.59 | H29: 26203 | I29: 98.28 | J29: 0.747 | K29: 17.01 | L29: 1.828221e+08 | M29: 1.7336791e+08 | N29: 45723.88
A30: Atalaia | B30: 4102208 | C30: atalaiense | D30: CARLOS EDUARDO ARMELIN MARIANI | E30: 137.075 | F30: 3980 | G30: 28.91 | H30: 4046 | I30: 98.9 | J30: 0.736 | K30: 32.26 | L30: 50133856 | M30: 45344327 | N30: 64007.95
A31: Balsa Nova | B31: 4102307 | C31: balsa-novense | D31: CLEVER APARECIDO IAVOLSKI POLETTO | E31: 347.588 | F31: 13395 | G31: 38.39 | H31: 13867 | I31: 99.25 | J31: 0.696 | K31: 6.54 | L31: 1.170218e+08 | M31: 1.1562185e+08 | N31: 97201.65
A32: Bandeirantes | B32: 4102406 | C32: bandeirantense | D32: JAELSON RAMALHO MATTA | E32: 445.192 | F32: 31273 | G32: 70.25 | H32: 31747 | I32: 99.78 | J32: 0.727 | K32: 2.8 | L32: 1.6204367e+08 | M32: 1.4577426e+08 | N32: 43559.41
A33: Barbosa Ferraz | B33: 4102505 | C33: barbosense | D33: CARLOS ROSA ALVES | E33: 536.101 | F33: 10795 | G33: 20.04 | H33: 10580 | I33: 97.97 | J33: 0.696 | K33: 16.26 | L33: 75370246 | M33: 72347928 | N33: 31695.71
A34: Barracão | B34: 4102604 | C34: barraconense | D34: JORGE LUIZ SANTIN | E34: 161.806 | F34: 9759 | G34: 60.53 | H34: 9903 | I34: 100 | J34: 0.706 | K34: 16.53 | L34: 76388436 | M34: 61353893 | N34: 33128.04
A35: Barra do Jacaré | B35: 4102703 | C35: barrense | D35: LUIZ FABIANO ZANATTA | E35: 115.855 | F35: 2814 | G35: 24.29 | H35: 2872 | I35: 100 | J35: 0.744 | K35: - | L35: 40385609 | M35: 32421151 | N35: 66502.51
A36: Bela Vista da Caroba | B36: 4102752 | C36: bela-vistense | D36: GELSON MAFFI | E36: 148.859 | F36: 4031 | G36: 27.22 | H36: 4122 | I36: 98.78 | J36: 0.681 | K36: - | L36: 41382475 | M36: 37302761 | N36: 31281.27
A37: Bela Vista do Paraíso | B37: 4102802 | C37: bela-vistense | D37: FABRICIO PASTORE | E37: 246.225 | F37: 14833 | G37: 61.12 | H37: 14982 | I37: 96.56 | J37: 0.716 | K37: 10.64 | L37: 1.1948572e+08 | M37: 1.0096663e+08 | N37: 38026.96
A38: Bituruna | B38: 4102901 | C38: biturenense | D38: RODRIGO ROSSONI | E38: 1280.76 | F38: 15533 | G38: 12.58 | H38: 15650 | I38: 98.35 | J38: 0.667 | K38: 7.72 | L38: 1.4071264e+08 | M38: 1.2695085e+08 | N38: 42256.96
A39: Boa Esperança | B39: 4103008 | C39: boa-esperansense | D39: JOEL CELSO BUSCARIOL | E39: 301.131 | F39: 4558 | G39: 15.06 | H39: 4595 | I39: 96.74 | J39: 0.72 | K39: 24.39 | L39: 71969832 | M39: 61581439 | N39: 75237.05
A40: Boa Esperança do Iguaçu | B40: 4103024 | C40: boaesperencense | D40: GIVANILDO TRUMI | E40: 152.252 | F40: 2455 | G40: 16.17 | H40: 2421 | I40: 100 | J40: 0.7 | K40: 34.48 | L40: 43954873 | M40: 38308780 | N40: 67222.53
A41: Boa Ventura de São Roque | B41: 4103040 | C41: boa venturense | D41: NESTOR KENEAR | E41: 606.94 | F41: 6378 | G41: 10.28 | H41: 6241 | I41: 99.8 | J41: 0.655 | K41: 11.76 | L41: 73000254 | M41: 64236260 | N41: 72838.58
A42: Boa Vista da Aparecida | B42: 4103057 | C42: boa-vistense | D42: EDUARDO JOSE HENRICHS | E42: 265.636 | F42: 7924 | G42: 29.77 | H42: 8023 | I42: 98.22 | J42: 0.67 | K42: 9.01 | L42: 69182923 | M42: 66289265 | N42: 28071.29
A43: Bocaiúva do Sul | B43: 4103107 | C43: bocaiuvense | D43: JOAO DE LIMA | E43: 809.682 | F43: 13299 | G43: 16.11 | H43: 13405 | I43: 98.99 | J43: 0.64 | K43: 5.81 | L43: 77778634 | M43: 71068933 | N43: 22971.54
A44: Bom Jesus do Sul | B44: 4103156 | C44: bonjesuense | D44: HELIO JOSE SURDI | E44: 175.536 | F44: 3980 | G44: 22.6 | H44: 4072 | I44: 100 | J44: 0.697 | K44: - | L44: 43583376 | M44: 37940796 | N44: 35783.31
A45: Bom Sucesso | B45: 4103206 | C45: bom-sucessense | D45: ROSANA FERREIRA LOPES | E45: 321.56 | F45: 6581 | G45: 20.39 | H45: 6674 | I45: 99.14 | J45: 0.686 | K45: 37.5 | L45: 54036266 | M45: 50544365 | N45: 33681.51
A46: Bom Sucesso do Sul | B46: 4103222 | C46: bomsucessense do sul | D46: MAICO DIOGO FAVERSANI | E46: 198.58 | F46: 3202 | G46: 16.34 | H46: 3244 | I46: 100 | J46: 0.742 | K46: - | L46: 54172649 | M46: 48287291 | N46: 103530.68
A47: Borrazópolis | B47: 4103305 | C47: borrazopolitano | D47: ADILSON LUCCHETTI | E47: 338.354 | F47: 7735 | G47: 23.13 | H47: 7818 | I47: 100 | J47: 0.717 | K47: 13.7 | L47: 59929207 | M47: 52503166 | N47: 38327.77
A48: Braganey | B48: 4103354 | C48: braganense | D48: VALDIR ZIELINSKI | E48: 343.26 | F48: 4854 | G48: 14.14 | H48: 4745 | I48: 100 | J48: 0.701 | K48: - | L48: 57149972 | M48: 57805709 | N48: 53771.59
A49: Brasilândia do Sul | B49: 4103370 | C49: brasilandiense | D49: ALEX ANTONIO CAVALCANTE | E49: 291.036 | F49: 3708 | G49: 12.74 | H49: 3861 | I49: 99.18 | J49: 0.681 | K49: - | L49: 51693906 | M49: 43785456 | N49: 80537.86
A50: Cafeara | B50: 4103404 | C50: cafearense | D50: ELTON FÁBIO LAZARETTI | E50: 184.255 | F50: 2627 | G50: 14.14 | H50: 2648 | I50: 98.89 | J50: 0.693 | K50: - | L50: 42776846 | M50: 40971513 | N50: 46262.76
A51: Cafelândia | B51: 4103453 | C51: cafelandense | D51: JUNIOR MOTTER | E51: 275.17 | F51: 18997 | G51: 69.1 | H51: 20145 | I51: 99.11 | J51: 0.748 | K51: 3.36 | L51: 1.6272405e+08 | M51: 1.5365451e+08 | N51: 142008.42
A52: Cafezal do Sul | B52: 4103479 | C52: cafezalense | D52: PEDRO MINORU INOUE | E52: 335.728 | F52: 4473 | G52: 13.34 | H52: 4580 | I52: 98.14 | J52: 0.692 | K52: - | L52: 50602155 | M52: 50181924 | N52: 44494.97
A53: Califórnia | B53: 4103503 | C53: californiano | D53: PAULO SÉRGIO CHILEIDE | E53: 141.817 | F53: 8710 | G53: 61.42 | H53: 8963 | I53: 99.58 | J53: 0.722 | K53: - | L53: 57772272 | M53: 52473109 | N53: 28817.34
A54: Cambará | B54: 4103602 | C54: cambaraense | D54: WALCIR JOAQUIM | E54: 367.462 | F54: 23212 | G54: 63.39 | H54: 23393 | I54: 100 | J54: 0.721 | K54: 12.35 | L54: 1.5177016e+08 | M54: 1.2805126e+08 | N54: 42457.02
A55: Cambé | B55: 4103701 | C55: cambeense | D55: CONRADO ANGELO SCHELLER | E55: 499.583 | F55: 107208 | G55: 216.42 | H55: 110923 | I55: 98.22 | J55: 0.734 | K55: 10.93 | L55: 5.6250434e+08 | M55: 5.8843019e+08 | N55: 63159.21
A56: Cambira | B56: 4103800 | C56: cambirense | D56: ANA LÚCIA DE OLIVEIRA | E56: 166.274 | F56: 9460 | G56: 57.41 | H56: 10045 | I56: 99.51 | J56: 0.725 | K56: 14.71 | L56: 65461704 | M56: 59743520 | N56: 36931.02
A57: Campina da Lagoa | B57: 4103909 | C57: campinense-da-lagoa | D57: GIANNY JOSE GRACIOSO BENTO | E57: 798.991 | F57: 15723 | G57: 19.74 | H57: 16014 | I57: 98.55 | J57: 0.704 | K57: 10.2 | L57: 105674392 | M57: 1.0343973e+08 | N57: 42893.99
A58: Campina do Simão | B58: 4103958 | C58: campineiro do simão | D58: ANDRÉ JUNIOR DE PAULA | E58: 448.033 | F58: 3936 | G58: 8.78 | H58: 3954 | I58: 100 | J58: 0.63 | K58: 24.69 | L58: 61586805 | M58: 48427438 | N58: 49573.09
A59: Campina Grande do Sul | B59: 4104006 | C59: campinense-do-sul | D59: LUIZ CARLOS ASSUNÇÃO | E59: 542.239 | F59: 47825 | G59: 88.69 | H59: 50600 | I59: 99.44 | J59: 0.718 | K59: 11.22 | L59: 3.3533383e+08 | M59: 2.9799479e+08 | N59: 60047.41
A60: Campo Bonito | B60: 4104055 | C60: campo-bonitense | D60: MARIO WEBER | E60: 434.124 | F60: 4027 | G60: 9.28 | H60: 3997 | I60: 100 | J60: 0.681 | K60: - | L60: 53000666 | M60: 50328576 | N60: 58901.77
A61: Campo do Tenente | B61: 4104105 | C61: tenentiano | D61: WEVERTON WILLIAN VIZENTIN | E61: 303.956 | F61: 7508 | G61: 24.66 | H61: 7693 | I61: 99.1 | J61: 0.686 | K61: - | L61: 60113770 | M61: 57573607 | N61: 40846.17
A62: Campo Largo | B62: 4104204 | C62: campo-larguense | D62: MAURICIO ROBERTO RIVABEM | E62: 1239.801 | F62: 136327 | G62: 109.63 | H62: 144504 | I62: 99.35 | J62: 0.745 | K62: 10.08 | L62: 7.5275276e+08 | M62: 6.7904208e+08 | N62: 51863.48
A63: Campo Magro | B63: 4104253 | C63: campomagrense | D63: RILTON BOZA | E63: 275.423 | F63: 30160 | G63: 109.53 | H63: 31888 | I63: 99.22 | J63: 0.701 | K63: 2.93 | L63: 1.5289187e+08 | M63: 1.4570328e+08 | N63: 23228.87
A64: Campo Mourão | B64: 4104303 | C64: mourãoense | D64: JOÃO DOUGLAS FABRÍCIO | E64: 748.054 | F64: 99432 | G64: 132.64 | H64: 104122 | I64: 99.15 | J64: 0.757 | K64: 6.88 | L64: 7.530185e+08 | M64: 7.1381299e+08 | N64: 60261.36
A65: Cândido de Abreu | B65: 4104402 | C65: cândido-abreuense | D65: RENAN MENCK ROMANICHEN | E65: 1506.15 | F65: 15244 | G65: 10.09 | H65: 15081 | I65: 98.78 | J65: 0.629 | K65: 10.42 | L65: 97683800 | M65: 90232657 | N65: 31175.22
A66: Candói | B66: 4104428 | C66: candoianos | D66: ALDOINO GOLDONI FILHO | E66: 1509.719 | F66: 14973 | G66: 9.9 | H66: 15174 | I66: 99.65 | J66: 0.635 | K66: 4.72 | L66: 1.3533259e+08 | M66: 1.2012785e+08 | N66: 60204.94
A67: Cantagalo | B67: 4104451 | C67: cantagalense | D67: JOAO KONJUNSKI | E67: 568.929 | F67: 10933 | G67: 18.74 | H67: 10672 | I67: 98.12 | J67: 0.635 | K67: 22.35 | L67: 67033604 | M67: 63685041 | N67: 35372.19
A68: Capanema | B68: 4104501 | C68: capanemense | D68: NEIVOR KESSLER | E68: 415.961 | F68: 20481 | G68: 48.88 | H68: 21088 | I68: 99.82 | J68: 0.706 | K68: 15.33 | L68: 1.394225e+08 | M68: 1.2666966e+08 | N68: 77763.81
A69: Capitão Leônidas Marques | B69: 4104600 | C69: leônidas-marquesiense | D69: MAXWELL SCAPINI | E69: 280.109 | F69: 14648 | G69: 52.3 | H69: 14776 | I69: 99.28 | J69: 0.716 | K69: 21.62 | L69: 1.1302736e+08 | M69: 98570194 | N69: 88764.32
A70: Carambeí | B70: 4104659 | C70: carambiense | D70: ELISANGELA PEDROSO DE OLIVEIRA NUNES | E70: 647.021 | F70: 23283 | G70: 35.84 | H70: 24469 | I70: 99.86 | J70: 0.728 | K70: 13.97 | L70: 2.0756392e+08 | M70: 1.7999506e+08 | N70: 85465.6
A71: Carlópolis | B71: 4104709 | C71: carlopolitano | D71: NILTON DOUGLAS DE MEIRA | E71: 454.169 | F71: 16905 | G71: 37.45 | H71: 17788 | I71: 98.51 | J71: 0.713 | K71: 4.29 | L71: 96088748 | M71: 71933659 | N71: 34061.74
A72: Cascavel | B72: 4104808 | C72: cascavelense | D72: RENATO DA SILVA | E72: 2094.263 | F72: 348051 | G72: 166.44 | H72: 368195 | I72: 99.15 | J72: 0.782 | K72: 11.24 | L72: 2.0823939e+09 | M72: 1.9850572e+09 | N72: 55176.33
A73: Castro | B73: 4104907 | C73: castrense | D73: REINALDO CARDOSO | E73: 2526.498 | F73: 73075 | G73: 28.87 | H73: 75644 | I73: 98.92 | J73: 0.703 | K73: 7.79 | L73: 4.9019903e+08 | M73: 4.1419653e+08 | N73: 61820.06
A74: Catanduvas | B74: 4105003 | C74: catanduvense | D74: ADEMAR LUIZ BURCKHARDT | E74: 578.494 | F74: 10446 | G74: 18 | H74: 10621 | I74: 99.32 | J74: 0.678 | K74: - | L74: 74799384 | M74: 72941318 | N74: 39602.22
A75: Centenário do Sul | B75: 4105102 | C75: centenariense | D75: MELQUIADES TAVIAN JUNIOR | E75: 370.629 | F75: 10832 | G75: 29.13 | H75: 10903 | I75: 98.99 | J75: 0.668 | K75: - | L75: 73399158 | M75: 67228058 | N75: 34760.43
A76: Cerro Azul | B76: 4105201 | C76: cerro-azulense | D76: EDSON CORDEIRO DO NASCIMENTO | E76: 1353.255 | F76: 16134 | G76: 12.03 | H76: 16287 | I76: 98.85 | J76: 0.573 | K76: 10.87 | L76: 99647815 | M76: 90190532 | N76: 23181.48
A77: Céu Azul | B77: 4105300 | C77: céu-azulense | D77: LAURINDO SPEROTTO | E77: 1176.523 | F77: 11087 | G77: 9.4 | H77: 11255 | I77: 99.09 | J77: 0.732 | K77: 26.32 | L77: 99071848 | M77: 82950920 | N77: 96562.03
A78: Chopinzinho | B78: 4105409 | C78: chopinzinhense | D78: ÁLVARO DÊNIS CENI SCOLARO | E78: 961.682 | F78: 21085 | G78: 21.97 | H78: 21604 | I78: 98.89 | J78: 0.74 | K78: 22.15 | L78: 1.9501591e+08 | M78: 1.7557198e+08 | N78: 56739.86
A79: Cianorte | B79: 4105508 | C79: cianortense | D79: MARCO ANTONIO FRANZATO | E79: 807.796 | F79: 79527 | G79: 97.98 | H79: 82988 | I79: 98.96 | J79: 0.755 | K79: 12.28 | L79: 5.9895866e+08 | M79: 5.5393212e+08 | N79: 50130.1
A80: Cidade Gaúcha | B80: 4105607 | C80: cidade-gauchense ou citadino | D80: ALEXANDRE LUCENA | E80: 402.241 | F80: 11467 | G80: 28.45 | H80: 11705 | I80: 98.71 | J80: 0.718 | K80: 14.71 | L80: 77712090 | M80: 64655686 | N80: 54113.89
A81: Clevelândia | B81: 4105706 | C81: clevelandense | D81: RAFAELA MARTINS LOSI | E81: 703.973 | F81: 15070 | G81: 21.42 | H81: 14833 | I81: 88.72 | J81: 0.694 | K81: 14.29 | L81: 1.31437e+08 | M81: 1.2484768e+08 | N81: 60754.81
A82: Colombo | B82: 4105805 | C82: colombense | D82: HELDER LUIZ LAZAROTTO | E82: 197.369 | F82: 232212 | G82: 1175.28 | H82: 241672 | I82: 98.49 | J82: 0.733 | K82: 11.51 | L82: 9.4880359e+08 | M82: 9.5591497e+08 | N82: 32853.49
A83: Colorado | B83: 4105904 | C83: colorado | D83: ROSIMEIRE CHIQUIM | E83: 408.533 | F83: 22896 | G83: 56.18 | H83: 23313 | I83: 99.08 | J83: 0.73 | K83: 20.69 | L83: 2.0782615e+08 | M83: 1.9036681e+08 | N83: 51174.35
A84: Congonhinhas | B84: 4106001 | C84: congonhinhense | D84: JOSE OLEGARIO RIBEIRO LOPES | E84: 535.963 | F84: 8320 | G84: 15.52 | H84: 8445 | I84: 99.03 | J84: 0.668 | K84: 11.24 | L84: 72304885 | M84: 71431530 | N84: 37201.52
A85: Conselheiro Mairinck | B85: 4106100 | C85: mairinquense | D85: JOSELEI APARECIDO DE CARVALHO | E85: 204.443 | F85: 3461 | G85: 16.91 | H85: 3474 | I85: 86.53 | J85: 0.707 | K85: - | L85: 40303215 | M85: 36631010 | N85: 48767.75
A86: Contenda | B86: 4106209 | C86: contendense | D86: ANTONIO ADAMIR DIGNER | E86: 296.488 | F86: 19128 | G86: 63.97 | H86: 20006 | I86: 99.05 | J86: 0.681 | K86: 4.24 | L86: 1.2808736e+08 | M86: 1.1685549e+08 | N86: 32821.93
A87: Corbélia | B87: 4106308 | C87: corbeliano | D87: THIAGO DAROSS STEFANELLO | E87: 527.607 | F87: 17470 | G87: 33.02 | H87: 17933 | I87: 98.66 | J87: 0.738 | K87: - | L87: 1.4540839e+08 | M87: 1.4071722e+08 | N87: 56867.78
A88: Cornélio Procópio | B88: 4106407 | C88: procopense | D88: RAPHAEL DIAS SAMPAIO | E88: 636.59 | F88: 45206 | G88: 71.18 | H88: 45720 | I88: 99.73 | J88: 0.759 | K88: 10.92 | L88: 2.5849542e+08 | M88: 2.3434328e+08 | N88: 52697.46
A89: Coronel Domingos Soares | B89: 4106456 | C89: domingosoarense | D89: MARIA ANTONIETA DE ARAUJO ALMEIDA | E89: 1511.972 | F89: 5649 | G89: 3.63 | H89: 5427 | I89: 98.77 | J89: 0.6 | K89: 8.77 | L89: 76956328 | M89: 67569619 | N89: 58230.22
A90: Coronel Vivida | B90: 4106506 | C90: coronel-vividense | D90: ANDERSON MANIQUE BARRETO | E90: 683.799 | F90: 23331 | G90: 34.09 | H90: 24010 | I90: 99.54 | J90: 0.723 | K90: 26.94 | L90: 1.7532588e+08 | M90: 1.7110531e+08 | N90: 47552.24
A91: Corumbataí do Sul | B91: 4106555 | C91: corumbataiense | D91: ALEXANDRE DONATO | E91: 167.921 | F91: 3760 | G91: 22.88 | H91: 3770 | I91: 97.85 | J91: 0.638 | K91: 28.57 | L91: 44525089 | M91: 40261446 | N91: 27908.16
A92: Cruzeiro do Iguaçu | B92: 4106571 | C92: cruzeirense | D92: RENI KOVALSKI | E92: 161.293 | F92: 4133 | G92: 25.53 | H92: 4129 | I92: 99.29 | J92: 0.709 | K92: - | L92: 51206595 | M92: 42637211 | N92: 50000.33
A93: Cruzeiro do Oeste | B93: 4106605 | C93: cruzeirense | D93: ARMANDO CERCI JUNIOR | E93: 776.101 | F93: 23831 | G93: 30.71 | H93: 24859 | I93: 100 | J93: 0.717 | K93: 26.92 | L93: 1.3885332e+08 | M93: 1.2788217e+08 | N93: 45708.09
A94: Cruzeiro do Sul | B94: 4106704 | C94: cruzeirense-do-sul | D94: MARCOS CÉSAR SUGIGAN | E94: 259.115 | F94: 4494 | G94: 17.34 | H94: 4543 | I94: 100 | J94: 0.713 | K94: - | L94: 51105250 | M94: 42602438 | N94: 62589.03
A95: Cruz Machado | B95: 4106803 | C95: cruz-machadense | D95: CARLOS NOWAK | E95: 1474.202 | F95: 15978 | G95: 10.81 | H95: 15759 | I95: 99.36 | J95: 0.664 | K95: 5.52 | L95: 1.1662364e+08 | M95: 1.0774349e+08 | N95: 31791.46
A96: Cruzmaltina | B96: 4106852 | C96: cruzmaltinense | D96: MAURÍCIO BUENO DE CAMARGO | E96: 306.237 | F96: 2892 | G96: 9.26 | H96: 2870 | I96: 100 | J96: 0.666 | K96: - | L96: 40718529 | M96: 36506773 | N96: 65430.04
A97: Curitiba | B97: 4106902 | C97: curitibano | D97: EDUARDO PIMENTEL SLAVIERO | E97: 435.406 | F97: 1773718 | G97: 4078.53 | H97: 1830795 | I97: 98.48 | J97: 0.823 | K97: 7.9 | L97: 1.3433545e+10 | M97: 1.4293532e+10 | N97: 67691.3
A98: Curiúva | B98: 4107009 | C98: curiuvense | D98: CHRISTIANO GIUNTA BORGES | E98: 576.263 | F98: 13647 | G98: 23.68 | H98: 13784 | I98: 99.17 | J98: 0.656 | K98: 11.76 | L98: 92157504 | M98: 81289937 | N98: 24397.6
A99: Diamante do Norte | B99: 4107108 | C99: diamantense | D99: ELIEL DOS SANTOS CORREA | E99: 242.887 | F99: 5142 | G99: 21.17 | H99: 5139 | I99: 99.4 | J99: 0.723 | K99: - | L99: 57445555 | M99: 55834570 | N99: 80500.47
A100: Diamante do Sul | B100: 4107124 | C100: sul-diamantino | D100: DARCI TIRELLI | E100: 347.233 | F100: 3171 | G100: 9.13 | H100: 3147 | I100: 100 | J100: 0.608 | K100: - | L100: 42252571 | M100: 33754783 | N100: 27043.14
A101: Diamante D'Oeste | B101: 4107157 | C101: diamantense | D101: AMARILDO APARECIDO DA SILVA | E101: 310.624 | F101: 4557 | G101: 14.74 | H101: 4513 | I101: 98 | J101: 0.644 | K101: 43.48 | L101: 46826281 | M101: 41596572 | N101: 29513.42
...

Sheet  IPDM Indice Geral (IPARDES-PR)
A1: ÍNDICE IPARDES DE DESEMPENHO MUNICIPAL - PARANÁ - 2010/2022
A2: MUNICÍPIO | B2: ÍNDICE GERAL
B3: 2010 | C3: 2011 | D3: 2012 | E3: 2013 | F3: 2014 | G3: 2015 | H3: 2016 | I3: 2017 | J3: 2018 | K3: 2019 | L3: 2020 | M3: 2021 | N3: 2022
A4: Abatiá | B4: 0.564077 | C4: 0.54537785 | D4: 0.5168096 | E4: 0.53849931 | F4: 0.56491834 | G4: 0.63262387 | H4: 0.63228917 | I4: 0.63481531 | J4: 0.61980948 | K4: 0.65180705 | L4: 0.65156887 | M4: 0.69398485 | N4: 0.7555704
A5: Adrianópolis | B5: 0.44702252 | C5: 0.51774727 | D5: 0.54219822 | E5: 0.6240232 | F5: 0.61340338 | G5: 0.58026342 | H5: 0.59700793 | I5: 0.6884003 | J5: 0.69522748 | K5: 0.69379038 | L5: 0.67694205 | M5: 0.64804303 | N5: 0.69505186
A6: Agudos do Sul | B6: 0.41218907 | C6: 0.39040514 | D6: 0.38284435 | E6: 0.46841146 | F6: 0.54175781 | G6: 0.55755044 | H6: 0.55591232 | I6: 0.6134253 | J6: 0.59386109 | K6: 0.60161727 | L6: 0.59952608 | M6: 0.63719632 | N6: 0.614756
A7: Almirante Tamandaré | B7: 0.46560314 | C7: 0.50093557 | D7: 0.50554893 | E7: 0.52758322 | F7: 0.53124223 | G7: 0.53629596 | H7: 0.54938697 | I7: 0.59062928 | J7: 0.59288951 | K7: 0.63356937 | L7: 0.62274966 | M7: 0.62891539 | N7: 0.62592222
A8: Altamira do Paraná | B8: 0.52746038 | C8: 0.58325804 | D8: 0.56894039 | E8: 0.59070921 | F8: 0.57473214 | G8: 0.62996768 | H8: 0.63854211 | I8: 0.67205014 | J8: 0.69105158 | K8: 0.73973884 | L8: 0.75979605 | M8: 0.74667674 | N8: 0.7449448
A9: Alto Paraíso | B9: 0.51674093 | C9: 0.62090236 | D9: 0.60484247 | E9: 0.63757084 | F9: 0.59763252 | G9: 0.5909948 | H9: 0.65410728 | I9: 0.67611671 | J9: 0.71527441 | K9: 0.74971128 | L9: 0.73644605 | M9: 0.74074011 | N9: 0.75700085
A10: Alto Paraná | B10: 0.61542114 | C10: 0.62627205 | D10: 0.61529839 | E10: 0.61672566 | F10: 0.617619 | G10: 0.62168758 | H10: 0.64343372 | I10: 0.66109416 | J10: 0.67096147 | K10: 0.73346029 | L10: 0.72169885 | M10: 0.68193607 | N10: 0.68877462
A11: Alto Piquiri | B11: 0.6144691 | C11: 0.59431878 | D11: 0.53084762 | E11: 0.52566575 | F11: 0.54450521 | G11: 0.58269402 | H11: 0.60277442 | I11: 0.65212971 | J11: 0.6903576 | K11: 0.70697085 | L11: 0.68806261 | M11: 0.7071396 | N11: 0.71459995
A12: Altônia | B12: 0.68519693 | C12: 0.65989594 | D12: 0.64756916 | E12: 0.67217854 | F12: 0.65007854 | G12: 0.63564396 | H12: 0.61774078 | I12: 0.66157555 | J12: 0.68307556 | K12: 0.73828174 | L12: 0.73196724 | M12: 0.75810472 | N12: 0.7592004
A13: Alvorada do Sul | B13: 0.59633112 | C13: 0.60243452 | D13: 0.63656075 | E13: 0.61689733 | F13: 0.63142697 | G13: 0.61273772 | H13: 0.6500504 | I13: 0.68729565 | J13: 0.7050665 | K13: 0.71872591 | L13: 0.7288429 | M13: 0.69390252 | N13: 0.74697634
A14: Amaporã | B14: 0.55930688 | C14: 0.56543578 | D14: 0.5318201 | E14: 0.49453741 | F14: 0.50533953 | G14: 0.53852545 | H14: 0.55469994 | I14: 0.61917962 | J14: 0.62509943 | K14: 0.69859649 | L14: 0.72773861 | M14: 0.70616801 | N14: 0.71318269
A15: Ampére | B15: 0.61433147 | C15: 0.67044207 | D15: 0.66506949 | E15: 0.7133545 | F15: 0.70491885 | G15: 0.67233182 | H15: 0.65435023 | I15: 0.67765526 | J15: 0.73048227 | K15: 0.77922695 | L15: 0.79242883 | M15: 0.79009542 | N15: 0.8023288
... A402: Xambrê | B402: 0.52002613 | C402: 0.53079954 | D402: 0.53966845 | E402: 0.58986729 | F402: 0.58944279 | G402: 0.58396123 | H402: 0.58837309 | I402: 0.66413115 | J402: 0.6697927 | K402: 0.67231606 | L402: 0.66409144 | M402: 0.64836173 | N402: 0.65966077

Sheet IPDM_renda  (IPARDES-PR)
A1: ÍNDICE IPARDES DE DESEMPENHO NA ÁREA DE RENDA E EMPREGO, DOS MUNICÍPIOS DO PARANÁ - 2010/2022
A2: MUNICÍPIO | B2: RENDA E EMPREGO
B3: 2010 | C3: 2011 | D3: 2012 | E3: 2013 | F3: 2014 | G3: 2015 | H3: 2016 | I3: 2017 | J3: 2018 | K3: 2019 | L3: 2020 | M3: 2021 | N3: 2022
A4: Abatiá | B4: 0.35587966 | C4: 0.38642798 | D4: 0.35624167 | E4: 0.36214147 | F4: 0.37757982 | G4: 0.38281657 | H4: 0.404298 | I4: 0.37172344 | J4: 0.36066858 | K4: 0.40461024 | L4: 0.380879 | M4: 0.41007672 | N4: 0.4662483
A5: Adrianópolis | B5: 0.50127807 | C5: 0.43630535 | D5: 0.47442738 | E5: 0.60318746 | F5: 0.57053328 | G5: 0.5690413 | H5: 0.55496635 | I5: 0.5316312 | J5: 0.51231986 | K5: 0.52736009 | L5: 0.47510438 | M5: 0.53345404 | N5: 0.55356135
A6: Agudos do Sul | B6: 0.40679223 | C6: 0.34462389 | D6: 0.34665753 | E6: 0.34024907 | F6: 0.36400023 | G6: 0.35071399 | H6: 0.31707017 | I6: 0.4180373 | J6: 0.33044431 | K6: 0.31281956 | L6: 0.32739033 | M6: 0.38104276 | N6: 0.40516741
A7: Almirante Tamandaré | B7: 0.414515 | C7: 0.43723334 | D7: 0.43956067 | E7: 0.42211824 | F7: 0.44002088 | G7: 0.39554102 | H7: 0.40080128 | I7: 0.4246826 | J7: 0.40480228 | K7: 0.41617175 | L7: 0.39767693 | M7: 0.42542019 | N7: 0.42379101
A8: Altamira do Paraná | B8: 0.33331812 | C8: 0.39283145 | D8: 0.35824221 | E8: 0.37020715 | F8: 0.3222926 | G8: 0.39285144 | H8: 0.37390599 | I8: 0.39780838 | J8: 0.38478178 | K8: 0.37268354 | L8: 0.39526593 | M8: 0.39366654 | N8: 0.47023497
A9: Alto Paraíso | B9: 0.46678796 | C9: 0.46143204 | D9: 0.45949927 | E9: 0.48575071 | F9: 0.49000744 | G9: 0.4476624 | H9: 0.47990754 | I9: 0.50327375 | J9: 0.49649181 | K9: 0.49123593 | L9: 0.51056115 | M9: 0.49395377 | N9: 0.55969746
A10: Alto Paraná | B10: 0.38880902 | C10: 0.40933165 | D10: 0.46617869 | E10: 0.45837128 | F10: 0.46422882 | G10: 0.37292429 | H10: 0.39276322 | I10: 0.42525665 | J10: 0.39862963 | K10: 0.39044119 | L10: 0.37369391 | M10: 0.40340382 | N10: 0.42681702
A11: Alto Piquiri | B11: 0.36919731 | C11: 0.39736992 | D11: 0.38362468 | E11: 0.39186271 | F11: 0.40461591 | G11: 0.37661051 | H11: 0.37867223 | I11: 0.42833265 | J11: 0.43077823 | K11: 0.41535838 | L11: 0.4104636 | M11: 0.45795584 | N11: 0.47223665
A12: Altônia | B12: 0.40357641 | C12: 0.41266942 | D12: 0.43152821 | E12: 0.43015009 | F12: 0.40378011 | G12: 0.39185313 | H12: 0.37912213 | I12: 0.38927564 | J12: 0.3748551 | K12: 0.40428675 | L12: 0.35519565 | M12: 0.40104356 | N12: 0.41552644
A13: Alvorada do Sul | B13: 0.38993406 | C13: 0.40855458 | D13: 0.44841322 | E13: 0.39863788 | F13: 0.40726847 | G13: 0.40170475 | H13: 0.42057168 | I13: 0.41187339 | J13: 0.42207268 | K13: 0.42178789 | L13: 0.43381731 | M13: 0.40941086 | N13: 0.48083085
A14: Amaporã | B14: 0.36835237 | C14: 0.3836105 | D14: 0.38322783 | E14: 0.40257187 | F14: 0.42588901 | G14: 0.37804183 | H14: 0.40638362 | I14: 0.41047618 | J14: 0.38978284 | K14: 0.39512407 | L14: 0.40622958 | M14: 0.43144541 | N14: 0.45027917
A15: Ampére | B15: 0.46549137 | C15: 0.46628969 | D15: 0.4791441 | E15: 0.50550129 | F15: 0.50623533 | G15: 0.46805522 | H15: 0.46799814 | I15: 0.49874118 | J15: 0.49713266 | K15: 0.50215169 | L15: 0.50490359 | M15: 0.51480444 | N15: 0.55149244
... A402: Xambrê | B402: 0.35521022 | C402: 0.35205804 | D402: 0.3955736 | E402: 0.36403857 | F402: 0.35542084 | G402: 0.34609006 | H402: 0.33853909 | I402: 0.35993388 | J402: 0.37901817 | K402: 0.34116002 | L402: 0.3640019 | M402: 0.33651761 | N402: 0.37612106

Sheet IPDM_educação  (IPARDES-PR)
A1: ÍNDICE IPARDES DE DESEMPENHO NA ÁREA DA EDUCAÇÃO, DOS MUNICÍPIOS DO PARANÁ - 2010/2022
A2: MUNICÍPIO | B2: EDUCAÇÃO
B3: 2010 | C3: 2011 | D3: 2012 | E3: 2013 | F3: 2014 | G3: 2015 | H3: 2016 | I3: 2017 | J3: 2018 | K3: 2019 | L3: 2020 | M3: 2021 | N3: 2022
A4: Abatiá | B4: 0.56315158 | C4: 0.54541292 | D4: 0.62936677 | E4: 0.62692667 | F4: 0.60847898 | G4: 0.66152118 | H4: 0.72820996 | I4: 0.83054769 | J4: 0.83172177 | K4: 0.87022741 | L4: 0.82255327 | M4: 0.84281088 | N4: 0.84839757
A5: Adrianópolis | B5: 0.41467132 | C5: 0.59466469 | D5: 0.47051475 | E5: 0.51933328 | F5: 0.56612363 | G5: 0.48705925 | H5: 0.52628198 | I5: 0.67402544 | J5: 0.68311417 | K5: 0.67991079 | L5: 0.7074198 | M5: 0.54836514 | N5: 0.5960072
A6: Agudos do Sul | B6: 0.31981299 | C6: 0.41604093 | D6: 0.35198045 | E6: 0.47551149 | F6: 0.55309974 | G6: 0.55480574 | H6: 0.59740486 | I6: 0.58523215 | J6: 0.64733151 | K6: 0.66225518 | L6: 0.64515009 | M6: 0.75401941 | N6: 0.73709325
A7: Almirante Tamandaré | B7: 0.2930783 | C7: 0.35720373 | D7: 0.34769181 | E7: 0.41327505 | F7: 0.39490772 | G7: 0.44702289 | H7: 0.46448815 | I7: 0.54142311 | J7: 0.55759042 | K7: 0.65102369 | L7: 0.63476892 | M7: 0.63837537 | N7: 0.65513361
A8: Altamira do Paraná | B8: 0.57520106 | C8: 0.60137128 | D8: 0.59277615 | E8: 0.62832838 | F8: 0.62085446 | G8: 0.68459422 | H8: 0.68596217 | I8: 0.70829641 | J8: 0.73226046 | K8: 0.86654669 | L8: 0.89441047 | M8: 0.85247481 | N8: 0.84725758
A9: Alto Paraíso | B9: 0.56255603 | C9: 0.69743451 | D9: 0.63594081 | E9: 0.64068536 | F9: 0.63095572 | G9: 0.70496996 | H9: 0.82990749 | I9: 0.74829691 | J9: 0.77781958 | K9: 0.88248615 | L9: 0.91377284 | M9: 0.95142748 | N9: 0.94486377
A10: Alto Paraná | B10: 0.71693528 | C10: 0.73065796 | D10: 0.64432002 | E10: 0.68402241 | F10: 0.70597655 | G10: 0.79546789 | H10: 0.8182954 | I10: 0.74090677 | J10: 0.74254292 | K10: 0.87353598 | L10: 0.87966851 | M10: 0.82831394 | N10: 0.8450197
A11: Alto Piquiri | B11: 0.68591425 | C11: 0.64821422 | D11: 0.62621162 | E11: 0.65562625 | F11: 0.65364396 | G11: 0.72675998 | H11: 0.75384445 | I11: 0.78197298 | J11: 0.81211279 | K11: 0.8770807 | L11: 0.88179123 | M11: 0.87949485 | N11: 0.88431273
A12: Altônia | B12: 0.86173833 | C12: 0.82912387 | D12: 0.78318676 | E12: 0.81433181 | F12: 0.81049 | G12: 0.81230015 | H12: 0.78813191 | I12: 0.83323487 | J12: 0.85239436 | K12: 0.90981247 | L12: 0.90814205 | M12: 0.92672187 | N12: 0.94073767
A13: Alvorada do Sul | B13: 0.5945411 | C13: 0.62888206 | D13: 0.63124261 | E13: 0.65544095 | F13: 0.67250148 | G13: 0.61570811 | H13: 0.65076577 | I13: 0.73362991 | J13: 0.75230913 | K13: 0.82189755 | L13: 0.81811441 | M13: 0.74801477 | N13: 0.80356727
A14: Amaporã | B14: 0.48695761 | C14: 0.55541962 | D14: 0.57101313 | E14: 0.4691901 | F14: 0.52002022 | G14: 0.59973983 | H14: 0.6099318 | I14: 0.63677726 | J14: 0.63813903 | K14: 0.76358908 | L14: 0.80021994 | M14: 0.74866589 | N14: 0.83922711
A15: Ampére | B15: 0.70735136 | C15: 0.7641827 | D15: 0.73158389 | E15: 0.82773135 | F15: 0.82406109 | G15: 0.81585788 | H15: 0.81673076 | I15: 0.8447087 | J15: 0.90890474 | K15: 0.94972264 | L15: 0.95607233 | M15: 0.94955837 | N15: 0.95062409
... A402: Xambrê | B402: 0.60259174 | C402: 0.65094243 | D402: 0.64399439 | E402: 0.73220473 | F402: 0.82582536 | G402: 0.8057076 | H402: 0.81041977 | I402: 0.8772801 | J402: 0.87098917 | K402: 0.90701724 | L402: 0.91216778 | M402: 0.89594093 | N402: 0.88070045

Sheet IPDM_saúde   (IPARDES-PR)
A1: ÍNDICE IPARDES DE DESEMPENHO NA ÁREA DA SAÚDE, DOS MUNICÍPIOS DO PARANÁ - 2010/2022
A2: MUNICÍPIO | B2: SAÚDE
B3: 2010 | C3: 2011 | D3: 2012 | E3: 2013 | F3: 2014 | G3: 2015 | H3: 2016 | I3: 2017 | J3: 2018 | K3: 2019 | L3: 2020 | M3: 2021 | N3: 2022
A4: Abatiá | B4: 0.77319976 | C4: 0.70429265 | D4: 0.56482036 | E4: 0.6264298 | F4: 0.7086962 | G4: 0.85353385 | H4: 0.76435954 | I4: 0.70217481 | J4: 0.66703809 | K4: 0.6805835 | L4: 0.75127436 | M4: 0.82906694 | N4: 0.95206532
A5: Adrianópolis | B5: 0.42511818 | C5: 0.52227177 | D5: 0.68165254 | E5: 0.74954887 | F5: 0.70355324 | G5: 0.68468971 | H5: 0.70977545 | I5: 0.85954426 | J5: 0.8902484 | K5: 0.87410026 | L5: 0.84830198 | M5: 0.8623099 | N5: 0.93558704
A6: Agudos do Sul | B6: 0.509962 | C6: 0.4105506 | D6: 0.44989508 | E6: 0.58947382 | F6: 0.70817345 | G6: 0.7671316 | H6: 0.75326192 | I6: 0.83700646 | J6: 0.80380746 | K6: 0.82977709 | L6: 0.82603781 | M6: 0.77652679 | N6: 0.70200735
A7: Almirante Tamandaré | B7: 0.68921612 | C7: 0.70836965 | D7: 0.72939431 | E7: 0.74735638 | F7: 0.75879808 | G7: 0.76632398 | H7: 0.78287149 | I7: 0.80578213 | J7: 0.81627583 | K7: 0.83351267 | L7: 0.83580313 | M7: 0.8229506 | N7: 0.79884205
A8: Altamira do Paraná | B8: 0.67386195 | C8: 0.7555714 | D8: 0.75580282 | E8: 0.77359211 | F8: 0.78104935 | G8: 0.81245737 | H8: 0.85575815 | I8: 0.91004563 | J8: 0.95611251 | K8: 0.97998629 | L8: 0.98971176 | M8: 0.99388887 | N8: 0.91734185
A9: Alto Paraíso | B9: 0.5208788 | C9: 0.70384053 | D9: 0.71908733 | E9: 0.78627645 | F9: 0.67193439 | G9: 0.62035205 | H9: 0.6525068 | I9: 0.77677946 | J9: 0.87151183 | K9: 0.87541175 | L9: 0.78500417 | M9: 0.77683906 | N9: 0.76644132
A10: Alto Paraná | B10: 0.74051912 | C10: 0.73882653 | D10: 0.73539647 | E10: 0.7077833 | F10: 0.68265163 | G10: 0.69667057 | H10: 0.71924255 | I10: 0.81711906 | J10: 0.87171186 | K10: 0.93640371 | L10: 0.91173412 | M10: 0.81409046 | N10: 0.79448714
A11: Alto Piquiri | B11: 0.78829574 | C11: 0.73737219 | D11: 0.58270656 | E11: 0.5295083 | F11: 0.57525576 | G11: 0.64471156 | H11: 0.67580658 | I11: 0.74608351 | J11: 0.82818178 | K11: 0.82847346 | L11: 0.77193301 | M11: 0.78396811 | N11: 0.78725047
A12: Altônia | B12: 0.79027605 | C12: 0.73789454 | D12: 0.72799252 | E12: 0.77205372 | F12: 0.73596552 | G12: 0.70277861 | H12: 0.6859683 | I12: 0.76221614 | J12: 0.82197722 | K12: 0.900746 | L12: 0.93256401 | M12: 0.94654874 | N12: 0.92133708
A13: Alvorada do Sul | B13: 0.80451819 | C13: 0.76986692 | D13: 0.83002641 | E13: 0.79661316 | F13: 0.81451095 | G13: 0.82080029 | H13: 0.87881374 | I13: 0.91638364 | J13: 0.94081769 | K13: 0.91249228 | L13: 0.93459698 | M13: 0.92428194 | N13: 0.95653088
A14: Amaporã | B14: 0.82261066 | C14: 0.75727721 | D14: 0.64121934 | E14: 0.61185027 | F14: 0.57010937 | G14: 0.63779469 | H14: 0.64778438 | I14: 0.81028543 | J14: 0.84737642 | K14: 0.93707632 | L14: 0.97676631 | M14: 0.93839273 | N14: 0.85004178
A15: Ampére | B15: 0.67015167 | C15: 0.78085384 | D15: 0.78448049 | E15: 0.80683086 | F15: 0.78446012 | G15: 0.73308236 | H15: 0.67832179 | I15: 0.68951589 | J15: 0.78540942 | K15: 0.88580651 | L15: 0.91631059 | M15: 0.90592344 | N15: 0.90486987
... A402: Xambrê | B402: 0.60227644 | C402: 0.58939816 | D402: 0.57943737 | E402: 0.67335856 | F402: 0.58708217 | G402: 0.60008605 | H402: 0.6161604 | I402: 0.75517947 | J402: 0.75937077 | K402: 0.76877091 | L402: 0.71610465 | M402: 0.71262667 | N402: 0.7221608
